{
"meta":{"test_sets":[],"test_metrics":[],"learn_metrics":[{"best_value":"Min","name":"RMSE"}],"launch_mode":"Train","parameters":"","iteration_count":1000,"learn_sets":["learn"],"name":"experiment"},
"iterations":[
{"learn":[0.9624955671],"iteration":0,"passed_time":0.04974923439,"remaining_time":49.69948515},
{"learn":[0.9283324408],"iteration":1,"passed_time":0.0521330853,"remaining_time":26.01440956},
{"learn":[0.8963404863],"iteration":2,"passed_time":0.05435702005,"remaining_time":18.06464966},
{"learn":[0.8640265076],"iteration":3,"passed_time":0.05655795537,"remaining_time":14.08293089},
{"learn":[0.8328696032],"iteration":4,"passed_time":0.05873961078,"remaining_time":11.68918254},
{"learn":[0.8037995136],"iteration":5,"passed_time":0.06099196053,"remaining_time":10.10433479},
{"learn":[0.7757217289],"iteration":6,"passed_time":0.06316158061,"remaining_time":8.959921364},
{"learn":[0.747788035],"iteration":7,"passed_time":0.0654643511,"remaining_time":8.117579537},
{"learn":[0.722888999],"iteration":8,"passed_time":0.06778952495,"remaining_time":7.464379914},
{"learn":[0.6991340635],"iteration":9,"passed_time":0.07013719437,"remaining_time":6.943582242},
{"learn":[0.6798561571],"iteration":10,"passed_time":0.07106222524,"remaining_time":6.389140069},
{"learn":[0.6583588642],"iteration":11,"passed_time":0.073263768,"remaining_time":6.032050232},
{"learn":[0.6385744093],"iteration":12,"passed_time":0.07543238235,"remaining_time":5.727058568},
{"learn":[0.620036693],"iteration":13,"passed_time":0.07766753315,"remaining_time":5.470013406},
{"learn":[0.6014636552],"iteration":14,"passed_time":0.07985215963,"remaining_time":5.243625149},
{"learn":[0.586445269],"iteration":15,"passed_time":0.08206907166,"remaining_time":5.047247907},
{"learn":[0.5701402998],"iteration":16,"passed_time":0.08433154419,"remaining_time":4.876347526},
{"learn":[0.553803838],"iteration":17,"passed_time":0.08661842351,"remaining_time":4.725516216},
{"learn":[0.5394951446],"iteration":18,"passed_time":0.08878761523,"remaining_time":4.584244765},
{"learn":[0.5239085703],"iteration":19,"passed_time":0.09098116162,"remaining_time":4.458076919},
{"learn":[0.5109197531],"iteration":20,"passed_time":0.09310408249,"remaining_time":4.340423655},
{"learn":[0.4991297834],"iteration":21,"passed_time":0.09527201454,"remaining_time":4.235274101},
{"learn":[0.4859650475],"iteration":22,"passed_time":0.09745362584,"remaining_time":4.139660541},
{"learn":[0.473753234],"iteration":23,"passed_time":0.09968137234,"remaining_time":4.053709142},
{"learn":[0.4623469492],"iteration":24,"passed_time":0.1019327317,"remaining_time":3.975376538},
{"learn":[0.451577384],"iteration":25,"passed_time":0.1042494768,"remaining_time":3.905345786},
{"learn":[0.4406863734],"iteration":26,"passed_time":0.1064626613,"remaining_time":3.83659887},
{"learn":[0.431529011],"iteration":27,"passed_time":0.1086965638,"remaining_time":3.773323573},
{"learn":[0.4218815657],"iteration":28,"passed_time":0.1107969256,"remaining_time":3.709786717},
{"learn":[0.4133380947],"iteration":29,"passed_time":0.1129922603,"remaining_time":3.653416416},
{"learn":[0.4049017611],"iteration":30,"passed_time":0.1153101494,"remaining_time":3.604372091},
{"learn":[0.3960624268],"iteration":31,"passed_time":0.1175209596,"remaining_time":3.555009028},
{"learn":[0.3881969442],"iteration":32,"passed_time":0.1197632487,"remaining_time":3.509426107},
{"learn":[0.380344969],"iteration":33,"passed_time":0.1219361567,"remaining_time":3.464421392},
{"learn":[0.3732146924],"iteration":34,"passed_time":0.1241299864,"remaining_time":3.422441053},
{"learn":[0.3668357601],"iteration":35,"passed_time":0.1262217069,"remaining_time":3.379936819},
{"learn":[0.3603277447],"iteration":36,"passed_time":0.1283517441,"remaining_time":3.340614313},
{"learn":[0.3542767584],"iteration":37,"passed_time":0.1305794846,"remaining_time":3.305722741},
{"learn":[0.3492355461],"iteration":38,"passed_time":0.1328659489,"remaining_time":3.273953254},
{"learn":[0.3438007159],"iteration":39,"passed_time":0.1350832626,"remaining_time":3.241998302},
{"learn":[0.3386410228],"iteration":40,"passed_time":0.1373610997,"remaining_time":3.212909624},
{"learn":[0.3326020995],"iteration":41,"passed_time":0.1395715102,"remaining_time":3.183559686},
{"learn":[0.327992825],"iteration":42,"passed_time":0.1418407703,"remaining_time":3.156781794},
{"learn":[0.3235554353],"iteration":43,"passed_time":0.1439818671,"remaining_time":3.128333294},
{"learn":[0.3187715194],"iteration":44,"passed_time":0.1461797765,"remaining_time":3.102259702},
{"learn":[0.3148133385],"iteration":45,"passed_time":0.1484417652,"remaining_time":3.078553131},
{"learn":[0.3107881041],"iteration":46,"passed_time":0.1506526816,"remaining_time":3.054723524},
{"learn":[0.3076361406],"iteration":47,"passed_time":0.1528556358,"remaining_time":3.031636776},
{"learn":[0.3040060875],"iteration":48,"passed_time":0.1551440628,"remaining_time":3.0110613},
{"learn":[0.3003093045],"iteration":49,"passed_time":0.1574211194,"remaining_time":2.991001268},
{"learn":[0.2967387042],"iteration":50,"passed_time":0.1597301648,"remaining_time":2.972233851},
{"learn":[0.2940090393],"iteration":51,"passed_time":0.1620170475,"remaining_time":2.953695404},
{"learn":[0.2910471902],"iteration":52,"passed_time":0.1642204814,"remaining_time":2.934279168},
{"learn":[0.2878237033],"iteration":53,"passed_time":0.1664677811,"remaining_time":2.916268906},
{"learn":[0.2852143092],"iteration":54,"passed_time":0.1686571649,"remaining_time":2.897836743},
{"learn":[0.2828447055],"iteration":55,"passed_time":0.1709244349,"remaining_time":2.881297617},
{"learn":[0.279977274],"iteration":56,"passed_time":0.1731735182,"remaining_time":2.86495838},
{"learn":[0.2777353439],"iteration":57,"passed_time":0.1753067543,"remaining_time":2.847223492},
{"learn":[0.2750266138],"iteration":58,"passed_time":0.1775445634,"remaining_time":2.831685325},
{"learn":[0.2729229151],"iteration":59,"passed_time":0.1796355295,"remaining_time":2.814289963},
{"learn":[0.2704590435],"iteration":60,"passed_time":0.1817507621,"remaining_time":2.797769928},
{"learn":[0.2685304887],"iteration":61,"passed_time":0.1839133915,"remaining_time":2.782431633},
{"learn":[0.2659999534],"iteration":62,"passed_time":0.1861527483,"remaining_time":2.768652781},
{"learn":[0.2638276349],"iteration":63,"passed_time":0.188421278,"remaining_time":2.75566119},
{"learn":[0.2619118823],"iteration":64,"passed_time":0.190681314,"remaining_time":2.742877363},
{"learn":[0.2596681015],"iteration":65,"passed_time":0.1928831368,"remaining_time":2.729588633},
{"learn":[0.2576043],"iteration":66,"passed_time":0.1950359816,"remaining_time":2.715948818},
{"learn":[0.2561405162],"iteration":67,"passed_time":0.1971736402,"remaining_time":2.702438716},
{"learn":[0.2540679569],"iteration":68,"passed_time":0.1993793455,"remaining_time":2.690176387},
{"learn":[0.2524000074],"iteration":69,"passed_time":0.2015400972,"remaining_time":2.677604148},
{"learn":[0.2512269659],"iteration":70,"passed_time":0.2037942432,"remaining_time":2.66654721},
{"learn":[0.2492379601],"iteration":71,"passed_time":0.2060176641,"remaining_time":2.655338781},
{"learn":[0.2473300767],"iteration":72,"passed_time":0.2081843598,"remaining_time":2.643656186},
{"learn":[0.2459644641],"iteration":73,"passed_time":0.210479561,"remaining_time":2.633838831},
{"learn":[0.2446102726],"iteration":74,"passed_time":0.2127311877,"remaining_time":2.623684648},
{"learn":[0.2431165227],"iteration":75,"passed_time":0.2149884598,"remaining_time":2.613807064},
{"learn":[0.2417934915],"iteration":76,"passed_time":0.2171433883,"remaining_time":2.602900615},
{"learn":[0.2409353156],"iteration":77,"passed_time":0.2194017022,"remaining_time":2.593440634},
{"learn":[0.2396536631],"iteration":78,"passed_time":0.2216341212,"remaining_time":2.583861084},
{"learn":[0.2380190376],"iteration":79,"passed_time":0.2238683818,"remaining_time":2.574486391},
{"learn":[0.2363283886],"iteration":80,"passed_time":0.2261147454,"remaining_time":2.565425321},
{"learn":[0.2350587341],"iteration":81,"passed_time":0.2282937899,"remaining_time":2.555776818},
{"learn":[0.2338851619],"iteration":82,"passed_time":0.2305115419,"remaining_time":2.546735951},
{"learn":[0.232597803],"iteration":83,"passed_time":0.2327259573,"remaining_time":2.537821154},
{"learn":[0.2312594764],"iteration":84,"passed_time":0.2350064481,"remaining_time":2.529775294},
{"learn":[0.2305336291],"iteration":85,"passed_time":0.2373051442,"remaining_time":2.522056998},
{"learn":[0.2295022248],"iteration":86,"passed_time":0.2395444736,"remaining_time":2.513840281},
{"learn":[0.2285314215],"iteration":87,"passed_time":0.2417877738,"remaining_time":2.505800565},
{"learn":[0.2272144691],"iteration":88,"passed_time":0.2440120661,"remaining_time":2.497696542},
{"learn":[0.2262698784],"iteration":89,"passed_time":0.2462414726,"remaining_time":2.489774889},
{"learn":[0.2252101392],"iteration":90,"passed_time":0.2484523502,"remaining_time":2.481793257},
{"learn":[0.2242110823],"iteration":91,"passed_time":0.2507914552,"remaining_time":2.475202624},
{"learn":[0.2228823376],"iteration":92,"passed_time":0.2530840495,"remaining_time":2.468249816},
{"learn":[0.2218604611],"iteration":93,"passed_time":0.255335455,"remaining_time":2.460999173},
{"learn":[0.221118276],"iteration":94,"passed_time":0.2576096488,"remaining_time":2.454070865},
{"learn":[0.2202977351],"iteration":95,"passed_time":0.2598408609,"remaining_time":2.446834773},
{"learn":[0.2196330421],"iteration":96,"passed_time":0.262175526,"remaining_time":2.440664948},
{"learn":[0.218898699],"iteration":97,"passed_time":0.2643444711,"remaining_time":2.433048091},
{"learn":[0.2180871693],"iteration":98,"passed_time":0.2665173844,"remaining_time":2.425577407},
{"learn":[0.2175172628],"iteration":99,"passed_time":0.2687306831,"remaining_time":2.418576148},
{"learn":[0.2169242152],"iteration":100,"passed_time":0.2708885552,"remaining_time":2.411176348},
{"learn":[0.2161417742],"iteration":101,"passed_time":0.2730870601,"remaining_time":2.404237059},
{"learn":[0.2153802463],"iteration":102,"passed_time":0.275265689,"remaining_time":2.397216728},
{"learn":[0.2146388012],"iteration":103,"passed_time":0.2775220877,"remaining_time":2.390959525},
{"learn":[0.2142009108],"iteration":104,"passed_time":0.2798230185,"remaining_time":2.38515811},
{"learn":[0.2133489656],"iteration":105,"passed_time":0.2820602616,"remaining_time":2.378885602},
{"learn":[0.2126139608],"iteration":106,"passed_time":0.2843283535,"remaining_time":2.372945978},
{"learn":[0.2118918901],"iteration":107,"passed_time":0.2865679576,"remaining_time":2.366839057},
{"learn":[0.2114044816],"iteration":108,"passed_time":0.2887437731,"remaining_time":2.360281668},
{"learn":[0.2107783158],"iteration":109,"passed_time":0.2909492372,"remaining_time":2.354043828},
{"learn":[0.2101568791],"iteration":110,"passed_time":0.2933252481,"remaining_time":2.349244554},
{"learn":[0.2090181696],"iteration":111,"passed_time":0.2956372225,"remaining_time":2.343980835},
{"learn":[0.2084736465],"iteration":112,"passed_time":0.2980022653,"remaining_time":2.339185923},
{"learn":[0.2078684444],"iteration":113,"passed_time":0.3000827404,"remaining_time":2.332222},
{"learn":[0.2068612615],"iteration":114,"passed_time":0.3023264376,"remaining_time":2.326599106},
{"learn":[0.2062781589],"iteration":115,"passed_time":0.3044435011,"remaining_time":2.32006944},
{"learn":[0.2056778981],"iteration":116,"passed_time":0.3067088084,"remaining_time":2.314733999},
{"learn":[0.2049904122],"iteration":117,"passed_time":0.3088678206,"remaining_time":2.308656083},
{"learn":[0.2043769546],"iteration":118,"passed_time":0.3111492128,"remaining_time":2.303550055},
{"learn":[0.203478826],"iteration":119,"passed_time":0.3134012431,"remaining_time":2.298275783},
{"learn":[0.202787105],"iteration":120,"passed_time":0.31559973,"remaining_time":2.292662501},
{"learn":[0.2022084079],"iteration":121,"passed_time":0.3178336893,"remaining_time":2.287360485},
{"learn":[0.2017524063],"iteration":122,"passed_time":0.3201416347,"remaining_time":2.282635884},
{"learn":[0.2012386232],"iteration":123,"passed_time":0.3224387912,"remaining_time":2.277874041},
{"learn":[0.2006368722],"iteration":124,"passed_time":0.3247076055,"remaining_time":2.272953239},
{"learn":[0.2002208234],"iteration":125,"passed_time":0.3269789953,"remaining_time":2.268092396},
{"learn":[0.1994526385],"iteration":126,"passed_time":0.3291884569,"remaining_time":2.262846637},
{"learn":[0.1986088374],"iteration":127,"passed_time":0.3313840789,"remaining_time":2.257554037},
{"learn":[0.1982529799],"iteration":128,"passed_time":0.3337270344,"remaining_time":2.25330424},
{"learn":[0.1977435584],"iteration":129,"passed_time":0.336070997,"remaining_time":2.249090518},
{"learn":[0.196843909],"iteration":130,"passed_time":0.3383227614,"remaining_time":2.244293738},
{"learn":[0.1965172112],"iteration":131,"passed_time":0.3406792137,"remaining_time":2.24022392},
{"learn":[0.1960620884],"iteration":132,"passed_time":0.342850195,"remaining_time":2.23497082},
{"learn":[0.1956343392],"iteration":133,"passed_time":0.3450727912,"remaining_time":2.230097293},
{"learn":[0.1952294904],"iteration":134,"passed_time":0.3472847141,"remaining_time":2.225194649},
{"learn":[0.1948229593],"iteration":135,"passed_time":0.3495382106,"remaining_time":2.220595691},
{"learn":[0.1940799602],"iteration":136,"passed_time":0.3517841985,"remaining_time":2.215983674},
{"learn":[0.1932121229],"iteration":137,"passed_time":0.3539678774,"remaining_time":2.211016741},
{"learn":[0.1925895779],"iteration":138,"passed_time":0.3560851729,"remaining_time":2.205678661},
{"learn":[0.1921157598],"iteration":139,"passed_time":0.3582190952,"remaining_time":2.200488728},
{"learn":[0.191695154],"iteration":140,"passed_time":0.3603222464,"remaining_time":2.195154678},
{"learn":[0.1911256938],"iteration":141,"passed_time":0.3624918257,"remaining_time":2.19026751},
{"learn":[0.1906117739],"iteration":142,"passed_time":0.3647701734,"remaining_time":2.1860702},
{"learn":[0.1896417607],"iteration":143,"passed_time":0.3670150861,"remaining_time":2.181700789},
{"learn":[0.1891569861],"iteration":144,"passed_time":0.3692839759,"remaining_time":2.177502065},
{"learn":[0.1887623739],"iteration":145,"passed_time":0.3714706967,"remaining_time":2.172849144},
{"learn":[0.1882885044],"iteration":146,"passed_time":0.3736267591,"remaining_time":2.168051874},
{"learn":[0.1875991955],"iteration":147,"passed_time":0.3758034407,"remaining_time":2.163408996},
{"learn":[0.1870349204],"iteration":148,"passed_time":0.3779126556,"remaining_time":2.158413892},
{"learn":[0.1866567307],"iteration":149,"passed_time":0.3801067827,"remaining_time":2.153938435},
{"learn":[0.1860100706],"iteration":150,"passed_time":0.3823152439,"remaining_time":2.149573789},
{"learn":[0.1855595836],"iteration":151,"passed_time":0.384507945,"remaining_time":2.145149588},
{"learn":[0.185233236],"iteration":152,"passed_time":0.3877046743,"remaining_time":2.146312805},
{"learn":[0.18485711],"iteration":153,"passed_time":0.3900269493,"remaining_time":2.142615579},
{"learn":[0.1845589484],"iteration":154,"passed_time":0.3923541326,"remaining_time":2.138962852},
{"learn":[0.1840258591],"iteration":155,"passed_time":0.3946409618,"remaining_time":2.135108793},
{"learn":[0.1834367224],"iteration":156,"passed_time":0.3968345536,"remaining_time":2.130774068},
{"learn":[0.1830275001],"iteration":157,"passed_time":0.3989952317,"remaining_time":2.126291045},
{"learn":[0.1825902275],"iteration":158,"passed_time":0.4011725936,"remaining_time":2.121925479},
{"learn":[0.1822562787],"iteration":159,"passed_time":0.4034141075,"remaining_time":2.117924065},
{"learn":[0.1814755433],"iteration":160,"passed_time":0.4055865443,"remaining_time":2.113584538},
{"learn":[0.181154431],"iteration":161,"passed_time":0.4078295819,"remaining_time":2.109636973},
{"learn":[0.1807662412],"iteration":162,"passed_time":0.4100210867,"remaining_time":2.105445703},
{"learn":[0.1804211642],"iteration":163,"passed_time":0.4122617901,"remaining_time":2.101529613},
{"learn":[0.1798517076],"iteration":164,"passed_time":0.4144431074,"remaining_time":2.097333301},
{"learn":[0.1795107505],"iteration":165,"passed_time":0.4166321971,"remaining_time":2.093200316},
{"learn":[0.1790142324],"iteration":166,"passed_time":0.4188766855,"remaining_time":2.08936694},
{"learn":[0.1786278685],"iteration":167,"passed_time":0.4209631161,"remaining_time":2.084769718},
{"learn":[0.1782819226],"iteration":168,"passed_time":0.423144261,"remaining_time":2.080667934},
{"learn":[0.1776388783],"iteration":169,"passed_time":0.4252817292,"remaining_time":2.076375501},
{"learn":[0.1769070741],"iteration":170,"passed_time":0.4273537341,"remaining_time":2.07179091},
{"learn":[0.1765959708],"iteration":171,"passed_time":0.4294463675,"remaining_time":2.067334839},
{"learn":[0.1761738812],"iteration":172,"passed_time":0.431599358,"remaining_time":2.063194619},
{"learn":[0.1758486463],"iteration":173,"passed_time":0.4338311187,"remaining_time":2.059451173},
{"learn":[0.1755304524],"iteration":174,"passed_time":0.4360571391,"remaining_time":2.055697942},
{"learn":[0.175322975],"iteration":175,"passed_time":0.4382721192,"remaining_time":2.051910376},
{"learn":[0.1749498501],"iteration":176,"passed_time":0.4403719237,"remaining_time":2.047605046},
{"learn":[0.1742994985],"iteration":177,"passed_time":0.4424584098,"remaining_time":2.043262994},
{"learn":[0.173622004],"iteration":178,"passed_time":0.4444964906,"remaining_time":2.038724127},
{"learn":[0.1734117163],"iteration":179,"passed_time":0.4466501587,"remaining_time":2.034739612},
{"learn":[0.1729812701],"iteration":180,"passed_time":0.4488425143,"remaining_time":2.030950382},
{"learn":[0.1726702116],"iteration":181,"passed_time":0.4509568253,"remaining_time":2.026827929},
{"learn":[0.1720274019],"iteration":182,"passed_time":0.4531124781,"remaining_time":2.022911992},
{"learn":[0.1717023526],"iteration":183,"passed_time":0.4551586368,"remaining_time":2.018529607},
{"learn":[0.1714052201],"iteration":184,"passed_time":0.4574040635,"remaining_time":2.015050334},
{"learn":[0.1712296362],"iteration":185,"passed_time":0.4596076992,"remaining_time":2.011401436},
{"learn":[0.1709982477],"iteration":186,"passed_time":0.4617610933,"remaining_time":2.007549566},
{"learn":[0.1704902241],"iteration":187,"passed_time":0.4639257188,"remaining_time":2.003764275},
{"learn":[0.1701393948],"iteration":188,"passed_time":0.4661145085,"remaining_time":2.000099822},
{"learn":[0.1698061482],"iteration":189,"passed_time":0.4683112806,"remaining_time":1.996484933},
{"learn":[0.16934561],"iteration":190,"passed_time":0.4705198528,"remaining_time":1.992934874},
{"learn":[0.16901029],"iteration":191,"passed_time":0.4726807728,"remaining_time":1.989198252},
{"learn":[0.1684711978],"iteration":192,"passed_time":0.4748404265,"remaining_time":1.985472664},
{"learn":[0.1681801376],"iteration":193,"passed_time":0.4770549087,"remaining_time":1.981991013},
{"learn":[0.1676471121],"iteration":194,"passed_time":0.4793507507,"remaining_time":1.978858227},
{"learn":[0.167221337],"iteration":195,"passed_time":0.481458867,"remaining_time":1.974963924},
{"learn":[0.1667163689],"iteration":196,"passed_time":0.4836574828,"remaining_time":1.971456643},
{"learn":[0.1663757494],"iteration":197,"passed_time":0.4859111758,"remaining_time":1.968185671},
{"learn":[0.1657996082],"iteration":198,"passed_time":0.488091359,"remaining_time":1.964629038},
{"learn":[0.1655619313],"iteration":199,"passed_time":0.4902521574,"remaining_time":1.96100863},
{"learn":[0.1653740841],"iteration":200,"passed_time":0.4924465986,"remaining_time":1.957536479},
{"learn":[0.1649900424],"iteration":201,"passed_time":0.4946258589,"remaining_time":1.954017007},
{"learn":[0.1645901453],"iteration":202,"passed_time":0.4967730155,"remaining_time":1.950384696},
{"learn":[0.1641901255],"iteration":203,"passed_time":0.4989762824,"remaining_time":1.946985886},
{"learn":[0.163983457],"iteration":204,"passed_time":0.5010718982,"remaining_time":1.943181264},
{"learn":[0.1637205352],"iteration":205,"passed_time":0.5032718365,"remaining_time":1.939795331},
{"learn":[0.1633493077],"iteration":206,"passed_time":0.5055035017,"remaining_time":1.9365424},
{"learn":[0.1631432103],"iteration":207,"passed_time":0.5076759024,"remaining_time":1.933073628},
{"learn":[0.1629066971],"iteration":208,"passed_time":0.509931151,"remaining_time":1.929930816},
{"learn":[0.162237283],"iteration":209,"passed_time":0.5120563613,"remaining_time":1.926307264},
{"learn":[0.1616851664],"iteration":210,"passed_time":0.5141788552,"remaining_time":1.922687757},
{"learn":[0.1613990215],"iteration":211,"passed_time":0.5162731379,"remaining_time":1.918977512},
{"learn":[0.1612073174],"iteration":212,"passed_time":0.5185430401,"remaining_time":1.915931327},
{"learn":[0.161003457],"iteration":213,"passed_time":0.5208227991,"remaining_time":1.912928599},
{"learn":[0.1607884723],"iteration":214,"passed_time":0.5231053775,"remaining_time":1.90994289},
{"learn":[0.1606100986],"iteration":215,"passed_time":0.5252435895,"remaining_time":1.906439695},
{"learn":[0.160290475],"iteration":216,"passed_time":0.5273351911,"remaining_time":1.902780897},
{"learn":[0.1597537592],"iteration":217,"passed_time":0.52942622,"remaining_time":1.899134422},
{"learn":[0.1593886293],"iteration":218,"passed_time":0.5315932098,"remaining_time":1.895773045},
{"learn":[0.1588681172],"iteration":219,"passed_time":0.533648366,"remaining_time":1.892026025},
{"learn":[0.1583488464],"iteration":220,"passed_time":0.5357869969,"remaining_time":1.888588555},
{"learn":[0.1578235064],"iteration":221,"passed_time":0.5379811695,"remaining_time":1.885357432},
{"learn":[0.1574153773],"iteration":222,"passed_time":0.5401584986,"remaining_time":1.882076921},
{"learn":[0.1571778282],"iteration":223,"passed_time":0.5423813922,"remaining_time":1.878964109},
{"learn":[0.1570027888],"iteration":224,"passed_time":0.5446590796,"remaining_time":1.876047941},
{"learn":[0.1565979082],"iteration":225,"passed_time":0.546780406,"remaining_time":1.872601921},
{"learn":[0.1563770193],"iteration":226,"passed_time":0.5490037774,"remaining_time":1.869515066},
{"learn":[0.1562259985],"iteration":227,"passed_time":0.551182407,"remaining_time":1.86628429},
{"learn":[0.1560141077],"iteration":228,"passed_time":0.5533818267,"remaining_time":1.8631327},
{"learn":[0.1557378844],"iteration":229,"passed_time":0.5555554596,"remaining_time":1.859903061},
{"learn":[0.1556068952],"iteration":230,"passed_time":0.5577381,"remaining_time":1.85671255},
{"learn":[0.1553753212],"iteration":231,"passed_time":0.5599989353,"remaining_time":1.853789579},
{"learn":[0.1552488647],"iteration":232,"passed_time":0.5622068506,"remaining_time":1.850698088},
{"learn":[0.1551472295],"iteration":233,"passed_time":0.5643860883,"remaining_time":1.847520272},
{"learn":[0.1549261648],"iteration":234,"passed_time":0.5665910412,"remaining_time":1.844434666},
{"learn":[0.1543109292],"iteration":235,"passed_time":0.5685823152,"remaining_time":1.840664783},
{"learn":[0.1541686305],"iteration":236,"passed_time":0.5706691875,"remaining_time":1.83721768},
{"learn":[0.1539555364],"iteration":237,"passed_time":0.572919044,"remaining_time":1.83430383},
{"learn":[0.1538823648],"iteration":238,"passed_time":0.5751771562,"remaining_time":1.831421824},
{"learn":[0.1535385593],"iteration":239,"passed_time":0.5774033416,"remaining_time":1.828443915},
{"learn":[0.1530979047],"iteration":240,"passed_time":0.5795322975,"remaining_time":1.825166032},
{"learn":[0.1528172553],"iteration":241,"passed_time":0.5816835599,"remaining_time":1.821967514},
{"learn":[0.1523808329],"iteration":242,"passed_time":0.5839776684,"remaining_time":1.819222613},
{"learn":[0.1522204094],"iteration":243,"passed_time":0.5862110102,"remaining_time":1.81629313},
{"learn":[0.152065033],"iteration":244,"passed_time":0.5883934181,"remaining_time":1.81321237},
{"learn":[0.1519558355],"iteration":245,"passed_time":0.5905502023,"remaining_time":1.810060376},
{"learn":[0.1516475591],"iteration":246,"passed_time":0.5927052871,"remaining_time":1.80691126},
{"learn":[0.151238491],"iteration":247,"passed_time":0.5949865076,"remaining_time":1.804152636},
{"learn":[0.1511029826],"iteration":248,"passed_time":0.5972095656,"remaining_time":1.801222425},
{"learn":[0.1508067593],"iteration":249,"passed_time":0.5992663088,"remaining_time":1.797798927},
{"learn":[0.1505011444],"iteration":250,"passed_time":0.6012851031,"remaining_time":1.794273077},
{"learn":[0.1502888439],"iteration":251,"passed_time":0.6033322127,"remaining_time":1.790843235},
{"learn":[0.1499927843],"iteration":252,"passed_time":0.6054346649,"remaining_time":1.787587726},
{"learn":[0.1496220268],"iteration":253,"passed_time":0.6075251792,"remaining_time":1.784306235},
{"learn":[0.1489106438],"iteration":254,"passed_time":0.6097442872,"remaining_time":1.78140978},
{"learn":[0.1487431607],"iteration":255,"passed_time":0.6119778809,"remaining_time":1.778560716},
{"learn":[0.1482015758],"iteration":256,"passed_time":0.6141907373,"remaining_time":1.775656489},
{"learn":[0.1481195481],"iteration":257,"passed_time":0.6164502608,"remaining_time":1.772891835},
{"learn":[0.1479048074],"iteration":258,"passed_time":0.6186986718,"remaining_time":1.770099289},
{"learn":[0.1475588179],"iteration":259,"passed_time":0.6208722627,"remaining_time":1.767097978},
{"learn":[0.1471885347],"iteration":260,"passed_time":0.6230208667,"remaining_time":1.764032262},
{"learn":[0.1469420113],"iteration":261,"passed_time":0.6252230203,"remaining_time":1.761124385},
{"learn":[0.1468280597],"iteration":262,"passed_time":0.6273565257,"remaining_time":1.758029504},
{"learn":[0.1467542523],"iteration":263,"passed_time":0.6295073102,"remaining_time":1.754990077},
{"learn":[0.146393135],"iteration":264,"passed_time":0.6316623209,"remaining_time":1.751969079},
{"learn":[0.1459497282],"iteration":265,"passed_time":0.6339523229,"remaining_time":1.749327087},
{"learn":[0.1455827853],"iteration":266,"passed_time":0.636211094,"remaining_time":1.746601992},
{"learn":[0.144998919],"iteration":267,"passed_time":0.6383894729,"remaining_time":1.743660799},
{"learn":[0.1448449581],"iteration":268,"passed_time":0.640732377,"remaining_time":1.74117237},
{"learn":[0.1446754929],"iteration":269,"passed_time":0.6429119555,"remaining_time":1.738243435},
{"learn":[0.1442031131],"iteration":270,"passed_time":0.6450242697,"remaining_time":1.735139087},
{"learn":[0.1436719017],"iteration":271,"passed_time":0.6471260756,"remaining_time":1.732013908},
{"learn":[0.1435709236],"iteration":272,"passed_time":0.6492299351,"remaining_time":1.728901695},
{"learn":[0.1434856767],"iteration":273,"passed_time":0.6514073397,"remaining_time":1.72599171},
{"learn":[0.1432292246],"iteration":274,"passed_time":0.6534968123,"remaining_time":1.722855232},
{"learn":[0.142834893],"iteration":275,"passed_time":0.6556677929,"remaining_time":1.719940152},
{"learn":[0.1426345839],"iteration":276,"passed_time":0.657831231,"remaining_time":1.717010758},
{"learn":[0.1425618539],"iteration":277,"passed_time":0.6600383677,"remaining_time":1.714200365},
{"learn":[0.1418795141],"iteration":278,"passed_time":0.6623063052,"remaining_time":1.71155142},
{"learn":[0.1414374358],"iteration":279,"passed_time":0.6645093396,"remaining_time":1.708738302},
{"learn":[0.1413362655],"iteration":280,"passed_time":0.6666867368,"remaining_time":1.705863928},
{"learn":[0.1412179638],"iteration":281,"passed_time":0.6687516409,"remaining_time":1.702708079},
{"learn":[0.141065535],"iteration":282,"passed_time":0.6710594748,"remaining_time":1.700175418},
{"learn":[0.1408767612],"iteration":283,"passed_time":0.6732306231,"remaining_time":1.69729974},
{"learn":[0.1403986243],"iteration":284,"passed_time":0.6754245471,"remaining_time":1.694486144},
{"learn":[0.1401952177],"iteration":285,"passed_time":0.6774971855,"remaining_time":1.691374093},
{"learn":[0.1397001258],"iteration":286,"passed_time":0.6797022687,"remaining_time":1.688598319},
{"learn":[0.1394007405],"iteration":287,"passed_time":0.6819539502,"remaining_time":1.68594171},
{"learn":[0.1389459765],"iteration":288,"passed_time":0.6841803328,"remaining_time":1.683225663},
{"learn":[0.1385879298],"iteration":289,"passed_time":0.6864223199,"remaining_time":1.680551197},
{"learn":[0.1385015685],"iteration":290,"passed_time":0.6885562817,"remaining_time":1.677616508},
{"learn":[0.1383065869],"iteration":291,"passed_time":0.6907091967,"remaining_time":1.674733258},
{"learn":[0.1379359837],"iteration":292,"passed_time":0.6928884878,"remaining_time":1.671918638},
{"learn":[0.1378221249],"iteration":293,"passed_time":0.6951618168,"remaining_time":1.669334159},
{"learn":[0.1376963466],"iteration":294,"passed_time":0.6973758373,"remaining_time":1.666610052},
{"learn":[0.1373772366],"iteration":295,"passed_time":0.6994948756,"remaining_time":1.663663488},
{"learn":[0.1370248593],"iteration":296,"passed_time":0.7015780004,"remaining_time":1.660637489},
{"learn":[0.1367846574],"iteration":297,"passed_time":0.7036623233,"remaining_time":1.657620641},
{"learn":[0.1364636841],"iteration":298,"passed_time":0.7058994114,"remaining_time":1.654968185},
{"learn":[0.1361403037],"iteration":299,"passed_time":0.708078637,"remaining_time":1.652183486},
{"learn":[0.1359801445],"iteration":300,"passed_time":0.7103479418,"remaining_time":1.649611998},
{"learn":[0.1358625728],"iteration":301,"passed_time":0.7125329191,"remaining_time":1.646847608},
{"learn":[0.1355421519],"iteration":302,"passed_time":0.7146353038,"remaining_time":1.643897052},
{"learn":[0.1353208244],"iteration":303,"passed_time":0.7168399726,"remaining_time":1.641186253},
{"learn":[0.1348173938],"iteration":304,"passed_time":0.7190332049,"remaining_time":1.638452713},
{"learn":[0.1344628156],"iteration":305,"passed_time":0.7212554189,"remaining_time":1.635788434},
{"learn":[0.1343365914],"iteration":306,"passed_time":0.7234036628,"remaining_time":1.63296006},
{"learn":[0.1341687041],"iteration":307,"passed_time":0.7256288873,"remaining_time":1.630309058},
{"learn":[0.1337994885],"iteration":308,"passed_time":0.7278340112,"remaining_time":1.627615863},
{"learn":[0.1336809091],"iteration":309,"passed_time":0.7300474116,"remaining_time":1.624944239},
{"learn":[0.1332551496],"iteration":310,"passed_time":0.7322395399,"remaining_time":1.622228434},
{"learn":[0.1329025714],"iteration":311,"passed_time":0.734447802,"remaining_time":1.619551563},
{"learn":[0.1327652053],"iteration":312,"passed_time":0.7366210868,"remaining_time":1.616800916},
{"learn":[0.1323985718],"iteration":313,"passed_time":0.73871085,"remaining_time":1.613871475},
{"learn":[0.1323076995],"iteration":314,"passed_time":0.7407139756,"remaining_time":1.610758963},
{"learn":[0.1321501715],"iteration":315,"passed_time":0.742816548,"remaining_time":1.607868731},
{"learn":[0.1319242019],"iteration":316,"passed_time":0.7448767656,"remaining_time":1.604892211},
{"learn":[0.1315882592],"iteration":317,"passed_time":0.7470074703,"remaining_time":1.602072625},
{"learn":[0.1312940577],"iteration":318,"passed_time":0.7490878071,"remaining_time":1.599149833},
{"learn":[0.1310072837],"iteration":319,"passed_time":0.7513275087,"remaining_time":1.596570956},
{"learn":[0.1306579136],"iteration":320,"passed_time":0.7540573944,"remaining_time":1.595031062},
{"learn":[0.1304360221],"iteration":321,"passed_time":0.7562729732,"remaining_time":1.592400857},
{"learn":[0.1302594475],"iteration":322,"passed_time":0.7584897423,"remaining_time":1.589775714},
{"learn":[0.1299200951],"iteration":323,"passed_time":0.7606811803,"remaining_time":1.58710024},
{"learn":[0.1295996514],"iteration":324,"passed_time":0.7628337965,"remaining_time":1.584347116},
{"learn":[0.1292399628],"iteration":325,"passed_time":0.7650859398,"remaining_time":1.581803446},
{"learn":[0.1291249514],"iteration":326,"passed_time":0.7674301677,"remaining_time":1.579451079},
{"learn":[0.1288758373],"iteration":327,"passed_time":0.7694627534,"remaining_time":1.576460275},
{"learn":[0.1287279061],"iteration":328,"passed_time":0.7715804191,"remaining_time":1.573648818},
{"learn":[0.1285471637],"iteration":329,"passed_time":0.7737947243,"remaining_time":1.571037774},
{"learn":[0.1284319898],"iteration":330,"passed_time":0.7760600563,"remaining_time":1.568532259},
{"learn":[0.1282255225],"iteration":331,"passed_time":0.7781810265,"remaining_time":1.565737728},
{"learn":[0.1280672964],"iteration":332,"passed_time":0.7803913341,"remaining_time":1.563126186},
{"learn":[0.1278101019],"iteration":333,"passed_time":0.7825680986,"remaining_time":1.560450161},
{"learn":[0.1275375159],"iteration":334,"passed_time":0.7847634974,"remaining_time":1.557814107},
{"learn":[0.1274163219],"iteration":335,"passed_time":0.786974075,"remaining_time":1.555210672},
{"learn":[0.1271253457],"iteration":336,"passed_time":0.7892196934,"remaining_time":1.552678507},
{"learn":[0.1269970472],"iteration":337,"passed_time":0.7914666162,"remaining_time":1.550150591},
{"learn":[0.1267386186],"iteration":338,"passed_time":0.7937094794,"remaining_time":1.547616418},
{"learn":[0.1265750042],"iteration":339,"passed_time":0.7958582698,"remaining_time":1.544901347},
{"learn":[0.1262806999],"iteration":340,"passed_time":0.7980125721,"remaining_time":1.542200249},
{"learn":[0.1260168958],"iteration":341,"passed_time":0.8001517951,"remaining_time":1.539473337},
{"learn":[0.1256182762],"iteration":342,"passed_time":0.8023728838,"remaining_time":1.536906661},
{"learn":[0.125347691],"iteration":343,"passed_time":0.8045766398,"remaining_time":1.534308941},
{"learn":[0.12500044],"iteration":344,"passed_time":0.8068146187,"remaining_time":1.531778479},
{"learn":[0.1248541484],"iteration":345,"passed_time":0.8089303892,"remaining_time":1.529018712},
{"learn":[0.1245867077],"iteration":346,"passed_time":0.8110272219,"remaining_time":1.52622702},
{"learn":[0.12454012],"iteration":347,"passed_time":0.8132128033,"remaining_time":1.523605597},
{"learn":[0.1242397567],"iteration":348,"passed_time":0.8153726401,"remaining_time":1.52093865},
{"learn":[0.124035229],"iteration":349,"passed_time":0.8175295673,"remaining_time":1.518269196},
{"learn":[0.1237798415],"iteration":350,"passed_time":0.8195400217,"remaining_time":1.515331835},
{"learn":[0.1236949399],"iteration":351,"passed_time":0.8217869171,"remaining_time":1.512835006},
{"learn":[0.123587943],"iteration":352,"passed_time":0.8239717588,"remaining_time":1.510225858},
{"learn":[0.1234424889],"iteration":353,"passed_time":0.826114559,"remaining_time":1.507542387},
{"learn":[0.1232283494],"iteration":354,"passed_time":0.8283766138,"remaining_time":1.505078636},
{"learn":[0.1230093014],"iteration":355,"passed_time":0.8307017569,"remaining_time":1.502730145},
{"learn":[0.1227869582],"iteration":356,"passed_time":0.8328407995,"remaining_time":1.500046594},
{"learn":[0.1226175057],"iteration":357,"passed_time":0.8351245922,"remaining_time":1.497625665},
{"learn":[0.1224145644],"iteration":358,"passed_time":0.8372519516,"remaining_time":1.494926187},
{"learn":[0.1221556084],"iteration":359,"passed_time":0.8392971287,"remaining_time":1.492083784},
{"learn":[0.1219241679],"iteration":360,"passed_time":0.8414506718,"remaining_time":1.489437616},
{"learn":[0.1217089583],"iteration":361,"passed_time":0.8435653791,"remaining_time":1.486725723},
{"learn":[0.1213964599],"iteration":362,"passed_time":0.8456866554,"remaining_time":1.484028649},
{"learn":[0.1210254155],"iteration":363,"passed_time":0.8478690018,"remaining_time":1.481441443},
{"learn":[0.1207308521],"iteration":364,"passed_time":0.8500802937,"remaining_time":1.478906812},
{"learn":[0.1204908273],"iteration":365,"passed_time":0.8522293081,"remaining_time":1.476266069},
{"learn":[0.120252693],"iteration":366,"passed_time":0.8545163184,"remaining_time":1.473866021},
{"learn":[0.1201370516],"iteration":367,"passed_time":0.8568333709,"remaining_time":1.47151818},
{"learn":[0.1198626756],"iteration":368,"passed_time":0.8589475857,"remaining_time":1.468823649},
{"learn":[0.1197315564],"iteration":369,"passed_time":0.86115511,"remaining_time":1.466291133},
{"learn":[0.119427426],"iteration":370,"passed_time":0.863417904,"remaining_time":1.463854074},
{"learn":[0.1193282926],"iteration":371,"passed_time":0.8656719879,"remaining_time":1.461403248},
{"learn":[0.1190238034],"iteration":372,"passed_time":0.8678356578,"remaining_time":1.458801494},
{"learn":[0.1187235996],"iteration":373,"passed_time":0.870102498,"remaining_time":1.456374769},
{"learn":[0.1183850883],"iteration":374,"passed_time":0.8723754469,"remaining_time":1.453959078},
{"learn":[0.1180754181],"iteration":375,"passed_time":0.8746098499,"remaining_time":1.451480176},
{"learn":[0.1179233578],"iteration":376,"passed_time":0.8768450608,"remaining_time":1.449003907},
{"learn":[0.1178275634],"iteration":377,"passed_time":0.8791479362,"remaining_time":1.446640255},
{"learn":[0.1175994208],"iteration":378,"passed_time":0.8813268177,"remaining_time":1.444073757},
{"learn":[0.1175243537],"iteration":379,"passed_time":0.8835172493,"remaining_time":1.441528144},
{"learn":[0.1174219883],"iteration":380,"passed_time":0.8857690605,"remaining_time":1.439084117},
{"learn":[0.1173113551],"iteration":381,"passed_time":0.8880044866,"remaining_time":1.436614588},
{"learn":[0.1171797301],"iteration":382,"passed_time":0.8902053785,"remaining_time":1.434090649},
{"learn":[0.1168282731],"iteration":383,"passed_time":0.8924283483,"remaining_time":1.431603809},
{"learn":[0.1167533766],"iteration":384,"passed_time":0.8945612723,"remaining_time":1.4289745},
{"learn":[0.1164867191],"iteration":385,"passed_time":0.8967887107,"remaining_time":1.426498105},
{"learn":[0.116332945],"iteration":386,"passed_time":0.8990188142,"remaining_time":1.424027217},
{"learn":[0.1161154079],"iteration":387,"passed_time":0.9012597821,"remaining_time":1.421574708},
{"learn":[0.1160512576],"iteration":388,"passed_time":0.9035013723,"remaining_time":1.419124263},
{"learn":[0.1157864982],"iteration":389,"passed_time":0.9057595566,"remaining_time":1.416700845},
{"learn":[0.1154429804],"iteration":390,"passed_time":0.9080078166,"remaining_time":1.414262814},
{"learn":[0.1151945126],"iteration":391,"passed_time":0.9101755469,"remaining_time":1.411700848},
{"learn":[0.1151291255],"iteration":392,"passed_time":0.9124094173,"remaining_time":1.409243044},
{"learn":[0.1147634891],"iteration":393,"passed_time":0.9145926464,"remaining_time":1.406708487},
{"learn":[0.114698141],"iteration":394,"passed_time":0.9168093733,"remaining_time":1.404227015},
{"learn":[0.1145134031],"iteration":395,"passed_time":0.9189996225,"remaining_time":1.401706495},
{"learn":[0.1143044354],"iteration":396,"passed_time":0.921170511,"remaining_time":1.399158232},
{"learn":[0.1142150297],"iteration":397,"passed_time":0.9234597192,"remaining_time":1.396790832},
{"learn":[0.1139826378],"iteration":398,"passed_time":0.9256031135,"remaining_time":1.394204188},
{"learn":[0.1137950771],"iteration":399,"passed_time":0.9278274739,"remaining_time":1.391741211},
{"learn":[0.1136233402],"iteration":400,"passed_time":0.9300124973,"remaining_time":1.389220663},
{"learn":[0.1133493085],"iteration":401,"passed_time":0.9322272348,"remaining_time":1.386745986},
{"learn":[0.1131251648],"iteration":402,"passed_time":0.9343455922,"remaining_time":1.384129823},
{"learn":[0.1129033259],"iteration":403,"passed_time":0.9363769664,"remaining_time":1.381387802},
{"learn":[0.1127034266],"iteration":404,"passed_time":0.9385346921,"remaining_time":1.378834918},
{"learn":[0.112648064],"iteration":405,"passed_time":0.940721179,"remaining_time":1.37632606},
{"learn":[0.1123535012],"iteration":406,"passed_time":0.9429663363,"remaining_time":1.373904269},
{"learn":[0.1121906157],"iteration":407,"passed_time":0.9450019553,"remaining_time":1.371179308},
{"learn":[0.1118976747],"iteration":408,"passed_time":0.9470716848,"remaining_time":1.368507007},
{"learn":[0.111765243],"iteration":409,"passed_time":0.9492021176,"remaining_time":1.365924998},
{"learn":[0.1115390428],"iteration":410,"passed_time":0.951476566,"remaining_time":1.363551575},
{"learn":[0.1112757038],"iteration":411,"passed_time":0.9536681296,"remaining_time":1.36106034},
{"learn":[0.1111917449],"iteration":412,"passed_time":0.9558429634,"remaining_time":1.358546779},
{"learn":[0.1109415969],"iteration":413,"passed_time":0.9579749994,"remaining_time":1.355974274},
{"learn":[0.1108055216],"iteration":414,"passed_time":0.9601347466,"remaining_time":1.353442956},
{"learn":[0.1104687381],"iteration":415,"passed_time":0.9622827666,"remaining_time":1.350896961},
{"learn":[0.1101907783],"iteration":416,"passed_time":0.9644386586,"remaining_time":1.34836388},
{"learn":[0.1099701291],"iteration":417,"passed_time":0.9665295439,"remaining_time":1.345742092},
{"learn":[0.1098127167],"iteration":418,"passed_time":0.9687201192,"remaining_time":1.343261072},
{"learn":[0.109661166],"iteration":419,"passed_time":0.9709890705,"remaining_time":1.340889669},
{"learn":[0.1095682459],"iteration":420,"passed_time":0.9732291637,"remaining_time":1.338479064},
{"learn":[0.1094009085],"iteration":421,"passed_time":0.9754614376,"remaining_time":1.336058557},
{"learn":[0.1091793641],"iteration":422,"passed_time":0.9776621965,"remaining_time":1.333595951},
{"learn":[0.1089768655],"iteration":423,"passed_time":0.9798853862,"remaining_time":1.331165053},
{"learn":[0.1087167896],"iteration":424,"passed_time":0.9820910214,"remaining_time":1.328711382},
{"learn":[0.1085379942],"iteration":425,"passed_time":0.9842740881,"remaining_time":1.326228466},
{"learn":[0.1082376399],"iteration":426,"passed_time":0.9864165649,"remaining_time":1.323692486},
{"learn":[0.1079387376],"iteration":427,"passed_time":0.9886162466,"remaining_time":1.321234797},
{"learn":[0.1076939899],"iteration":428,"passed_time":0.9907815771,"remaining_time":1.318732589},
{"learn":[0.1074470585],"iteration":429,"passed_time":0.9929319854,"remaining_time":1.316212167},
{"learn":[0.1073047909],"iteration":430,"passed_time":0.995081668,"remaining_time":1.313692504},
{"learn":[0.1071342969],"iteration":431,"passed_time":0.9971929746,"remaining_time":1.311124096},
{"learn":[0.1070571638],"iteration":432,"passed_time":0.9993562489,"remaining_time":1.30862585},
{"learn":[0.1068055577],"iteration":433,"passed_time":1.00156923,"remaining_time":1.306193972},
{"learn":[0.1065954526],"iteration":434,"passed_time":1.003809849,"remaining_time":1.303798999},
{"learn":[0.106375946],"iteration":435,"passed_time":1.00600881,"remaining_time":1.301350846},
{"learn":[0.1061893746],"iteration":436,"passed_time":1.008031273,"remaining_time":1.298676445},
{"learn":[0.1059588221],"iteration":437,"passed_time":1.010121555,"remaining_time":1.296092041},
{"learn":[0.1057893002],"iteration":438,"passed_time":1.01235485,"remaining_time":1.293692644},
{"learn":[0.1057331307],"iteration":439,"passed_time":1.014473666,"remaining_time":1.291148302},
{"learn":[0.1055218676],"iteration":440,"passed_time":1.016617093,"remaining_time":1.288637086},
{"learn":[0.1054639904],"iteration":441,"passed_time":1.01871637,"remaining_time":1.286071798},
{"learn":[0.1053381953],"iteration":442,"passed_time":1.02085832,"remaining_time":1.283562267},
{"learn":[0.1051611741],"iteration":443,"passed_time":1.023053878,"remaining_time":1.281121524},
{"learn":[0.1051074031],"iteration":444,"passed_time":1.025291186,"remaining_time":1.278733952},
{"learn":[0.104768562],"iteration":445,"passed_time":1.027523299,"remaining_time":1.2763406},
{"learn":[0.1046030576],"iteration":446,"passed_time":1.029816226,"remaining_time":1.274023205},
{"learn":[0.1044265999],"iteration":447,"passed_time":1.031913546,"remaining_time":1.271464904},
{"learn":[0.1042884632],"iteration":448,"passed_time":1.034086072,"remaining_time":1.269000948},
{"learn":[0.1040245071],"iteration":449,"passed_time":1.036273089,"remaining_time":1.266555998},
{"learn":[0.1038075192],"iteration":450,"passed_time":1.038344645,"remaining_time":1.263971641},
{"learn":[0.1036187553],"iteration":451,"passed_time":1.040416689,"remaining_time":1.261390145},
{"learn":[0.1034368757],"iteration":452,"passed_time":1.042677921,"remaining_time":1.259039343},
{"learn":[0.1032663224],"iteration":453,"passed_time":1.044894194,"remaining_time":1.256634868},
{"learn":[0.1031980262],"iteration":454,"passed_time":1.046933761,"remaining_time":1.25401956},
{"learn":[0.1031468446],"iteration":455,"passed_time":1.049060353,"remaining_time":1.251510597},
{"learn":[0.1028612947],"iteration":456,"passed_time":1.051126869,"remaining_time":1.248931925},
{"learn":[0.1027703532],"iteration":457,"passed_time":1.053387072,"remaining_time":1.246584701},
{"learn":[0.1026562611],"iteration":458,"passed_time":1.055587542,"remaining_time":1.244167452},
{"learn":[0.1026004734],"iteration":459,"passed_time":1.057773802,"remaining_time":1.241734463},
{"learn":[0.1025510188],"iteration":460,"passed_time":1.060019287,"remaining_time":1.239371791},
{"learn":[0.1023326021],"iteration":461,"passed_time":1.062300816,"remaining_time":1.2370516},
{"learn":[0.1022259195],"iteration":462,"passed_time":1.064487139,"remaining_time":1.234621153},
{"learn":[0.1020963398],"iteration":463,"passed_time":1.066704435,"remaining_time":1.232227537},
{"learn":[0.1019025145],"iteration":464,"passed_time":1.068902868,"remaining_time":1.229812977},
{"learn":[0.1016980456],"iteration":465,"passed_time":1.071046501,"remaining_time":1.227336548},
{"learn":[0.1014725283],"iteration":466,"passed_time":1.073175573,"remaining_time":1.224844925},
{"learn":[0.1012679772],"iteration":467,"passed_time":1.075341261,"remaining_time":1.222396476},
{"learn":[0.1010542907],"iteration":468,"passed_time":1.07752399,"remaining_time":1.219968526},
{"learn":[0.1008233568],"iteration":469,"passed_time":1.079774223,"remaining_time":1.21761774},
{"learn":[0.1006588031],"iteration":470,"passed_time":1.082000141,"remaining_time":1.215240074},
{"learn":[0.1005340808],"iteration":471,"passed_time":1.084277241,"remaining_time":1.212920303},
{"learn":[0.1004667807],"iteration":472,"passed_time":1.086379259,"remaining_time":1.210405643},
{"learn":[0.100298999],"iteration":473,"passed_time":1.088553238,"remaining_time":1.207972581},
{"learn":[0.1001975922],"iteration":474,"passed_time":1.090705146,"remaining_time":1.205516214},
{"learn":[0.09991376562],"iteration":475,"passed_time":1.092792617,"remaining_time":1.202990191},
{"learn":[0.09972414384],"iteration":476,"passed_time":1.094985679,"remaining_time":1.200581782},
{"learn":[0.09960681551],"iteration":477,"passed_time":1.097181738,"remaining_time":1.198177547},
{"learn":[0.09951588365],"iteration":478,"passed_time":1.099334685,"remaining_time":1.195727288},
{"learn":[0.09933170949],"iteration":479,"passed_time":1.101310472,"remaining_time":1.193086344},
{"learn":[0.09921308445],"iteration":480,"passed_time":1.103371375,"remaining_time":1.190540007},
{"learn":[0.09910085009],"iteration":481,"passed_time":1.105459079,"remaining_time":1.188024487},
{"learn":[0.09897660851],"iteration":482,"passed_time":1.10761564,"remaining_time":1.185584443},
{"learn":[0.09887984575],"iteration":483,"passed_time":1.109851967,"remaining_time":1.183230609},
{"learn":[0.0986789415],"iteration":484,"passed_time":1.11205826,"remaining_time":1.180845369},
{"learn":[0.09842350912],"iteration":485,"passed_time":1.114246081,"remaining_time":1.178441329},
{"learn":[0.0982076511],"iteration":486,"passed_time":1.116544043,"remaining_time":1.176154197},
{"learn":[0.09810929664],"iteration":487,"passed_time":1.118730954,"remaining_time":1.173750509},
{"learn":[0.09793744678],"iteration":488,"passed_time":1.120967242,"remaining_time":1.171399306},
{"learn":[0.09790838009],"iteration":489,"passed_time":1.123125893,"remaining_time":1.168967766},
{"learn":[0.09786951833],"iteration":490,"passed_time":1.125352062,"remaining_time":1.166607331},
{"learn":[0.09778078143],"iteration":491,"passed_time":1.127629098,"remaining_time":1.164299963},
{"learn":[0.09754067583],"iteration":492,"passed_time":1.12979823,"remaining_time":1.16188175},
{"learn":[0.09743374039],"iteration":493,"passed_time":1.13197378,"remaining_time":1.159471118},
{"learn":[0.09713456609],"iteration":494,"passed_time":1.134117245,"remaining_time":1.157028704},
{"learn":[0.09708687015],"iteration":495,"passed_time":1.136332762,"remaining_time":1.15466071},
{"learn":[0.09705292024],"iteration":496,"passed_time":1.138496203,"remaining_time":1.152240624},
{"learn":[0.09691470563],"iteration":497,"passed_time":1.140688886,"remaining_time":1.149851046},
{"learn":[0.09679526288],"iteration":498,"passed_time":1.14294834,"remaining_time":1.147529296},
{"learn":[0.09664205237],"iteration":499,"passed_time":1.145156855,"remaining_time":1.145156855},
{"learn":[0.09640023832],"iteration":500,"passed_time":1.147367612,"remaining_time":1.142787303},
{"learn":[0.09625688372],"iteration":501,"passed_time":1.149645413,"remaining_time":1.140484892},
{"learn":[0.09608176569],"iteration":502,"passed_time":1.151776984,"remaining_time":1.138038094},
{"learn":[0.09606011583],"iteration":503,"passed_time":1.152665114,"remaining_time":1.134368842},
{"learn":[0.09592502014],"iteration":504,"passed_time":1.154743119,"remaining_time":1.131876918},
{"learn":[0.09587849009],"iteration":505,"passed_time":1.156873601,"remaining_time":1.129437864},
{"learn":[0.09572011318],"iteration":506,"passed_time":1.159139533,"remaining_time":1.127131735},
{"learn":[0.09556535631],"iteration":507,"passed_time":1.161339619,"remaining_time":1.124761993},
{"learn":[0.09541571005],"iteration":508,"passed_time":1.163453738,"remaining_time":1.122309991},
{"learn":[0.09525799006],"iteration":509,"passed_time":1.165552471,"remaining_time":1.119844531},
{"learn":[0.09509262013],"iteration":510,"passed_time":1.167734,"remaining_time":1.117459738},
{"learn":[0.09503760492],"iteration":511,"passed_time":1.170044272,"remaining_time":1.115198447},
{"learn":[0.09494938721],"iteration":512,"passed_time":1.172309239,"remaining_time":1.112893956},
{"learn":[0.09488519278],"iteration":513,"passed_time":1.174462084,"remaining_time":1.110483605},
{"learn":[0.09468256072],"iteration":514,"passed_time":1.17653872,"remaining_time":1.108002484},
{"learn":[0.09457409776],"iteration":515,"passed_time":1.178604052,"remaining_time":1.105512328},
{"learn":[0.09446395881],"iteration":516,"passed_time":1.180848925,"remaining_time":1.103191549},
{"learn":[0.09435886623],"iteration":517,"passed_time":1.182959878,"remaining_time":1.10074645},
{"learn":[0.09424438128],"iteration":518,"passed_time":1.185068964,"remaining_time":1.098300909},
{"learn":[0.09402283743],"iteration":519,"passed_time":1.187225706,"remaining_time":1.095900652},
{"learn":[0.09399550606],"iteration":520,"passed_time":1.189460542,"remaining_time":1.093573128},
{"learn":[0.09388795767],"iteration":521,"passed_time":1.191740925,"remaining_time":1.091287667},
{"learn":[0.0937307874],"iteration":522,"passed_time":1.194039077,"remaining_time":1.089018432},
{"learn":[0.09363691588],"iteration":523,"passed_time":1.196162787,"remaining_time":1.086590623},
{"learn":[0.09361111431],"iteration":524,"passed_time":1.198237829,"remaining_time":1.084119941},
{"learn":[0.09347234023],"iteration":525,"passed_time":1.200414263,"remaining_time":1.081742131},
{"learn":[0.09329604689],"iteration":526,"passed_time":1.202585211,"remaining_time":1.079360161},
{"learn":[0.09323257451],"iteration":527,"passed_time":1.204715371,"remaining_time":1.076942529},
{"learn":[0.0931771776],"iteration":528,"passed_time":1.206781433,"remaining_time":1.074468913},
{"learn":[0.09302983439],"iteration":529,"passed_time":1.209000858,"remaining_time":1.072132836},
{"learn":[0.09282363376],"iteration":530,"passed_time":1.211246118,"remaining_time":1.069820018},
{"learn":[0.09266450473],"iteration":531,"passed_time":1.213445708,"remaining_time":1.067467277},
{"learn":[0.0925425357],"iteration":532,"passed_time":1.215593233,"remaining_time":1.065069493},
{"learn":[0.09247885656],"iteration":533,"passed_time":1.217704059,"remaining_time":1.062640621},
{"learn":[0.0923113901],"iteration":534,"passed_time":1.219923717,"remaining_time":1.06030753},
{"learn":[0.09216510636],"iteration":535,"passed_time":1.2221289,"remaining_time":1.057962331},
{"learn":[0.09205340588],"iteration":536,"passed_time":1.224411244,"remaining_time":1.055684182},
{"learn":[0.09186913985],"iteration":537,"passed_time":1.2265726,"remaining_time":1.053302121},
{"learn":[0.09181006572],"iteration":538,"passed_time":1.228748879,"remaining_time":1.050933642},
{"learn":[0.09171865267],"iteration":539,"passed_time":1.230824399,"remaining_time":1.048480044},
{"learn":[0.09159376378],"iteration":540,"passed_time":1.233082447,"remaining_time":1.046182705},
{"learn":[0.09153779642],"iteration":541,"passed_time":1.235385659,"remaining_time":1.043923675},
{"learn":[0.09143559194],"iteration":542,"passed_time":1.237508739,"remaining_time":1.04151288},
{"learn":[0.09136806226],"iteration":543,"passed_time":1.23960291,"remaining_time":1.03907891},
{"learn":[0.09114526543],"iteration":544,"passed_time":1.241627011,"remaining_time":1.036587688},
{"learn":[0.09088901723],"iteration":545,"passed_time":1.243673488,"remaining_time":1.034116783},
{"learn":[0.09066971763],"iteration":546,"passed_time":1.245905421,"remaining_time":1.031801016},
{"learn":[0.0905157563],"iteration":547,"passed_time":1.248180681,"remaining_time":1.029521292},
{"learn":[0.09035787912],"iteration":548,"passed_time":1.250455055,"remaining_time":1.027240856},
{"learn":[0.09032319653],"iteration":549,"passed_time":1.252667487,"remaining_time":1.024909762},
{"learn":[0.09008411252],"iteration":550,"passed_time":1.254902247,"remaining_time":1.022597293},
{"learn":[0.08997599886],"iteration":551,"passed_time":1.25716589,"remaining_time":1.020308548},
{"learn":[0.08982718233],"iteration":552,"passed_time":1.259453766,"remaining_time":1.018039482},
{"learn":[0.08968082464],"iteration":553,"passed_time":1.261675508,"remaining_time":1.015717106},
{"learn":[0.08951093877],"iteration":554,"passed_time":1.263900759,"remaining_time":1.013397906},
{"learn":[0.08928419462],"iteration":555,"passed_time":1.266067248,"remaining_time":1.011032119},
{"learn":[0.08917572892],"iteration":556,"passed_time":1.268270945,"remaining_time":1.00869664},
{"learn":[0.08909501596],"iteration":557,"passed_time":1.27046611,"remaining_time":1.006354875},
{"learn":[0.08898119963],"iteration":558,"passed_time":1.272748349,"remaining_time":1.004082329},
{"learn":[0.08887212331],"iteration":559,"passed_time":1.27501173,"remaining_time":1.001794931},
{"learn":[0.08863681565],"iteration":560,"passed_time":1.27722788,"remaining_time":0.999470658},
{"learn":[0.08849500138],"iteration":561,"passed_time":1.279435163,"remaining_time":0.9971398599},
{"learn":[0.08844503863],"iteration":562,"passed_time":1.28167452,"remaining_time":0.9948343967},
{"learn":[0.08830825749],"iteration":563,"passed_time":1.283857544,"remaining_time":0.9924856188},
{"learn":[0.08817829157],"iteration":564,"passed_time":1.286075177,"remaining_time":0.990164074},
{"learn":[0.08804748524],"iteration":565,"passed_time":1.28815699,"remaining_time":0.9877387517},
{"learn":[0.08796226904],"iteration":566,"passed_time":1.290309815,"remaining_time":0.9853688711},
{"learn":[0.08785119557],"iteration":567,"passed_time":1.292563711,"remaining_time":0.9830766253},
{"learn":[0.0877441752],"iteration":568,"passed_time":1.294791178,"remaining_time":0.9807644948},
{"learn":[0.08764285147],"iteration":569,"passed_time":1.296970755,"remaining_time":0.9784165348},
{"learn":[0.08761319514],"iteration":570,"passed_time":1.299136223,"remaining_time":0.9760585633},
{"learn":[0.08749310025],"iteration":571,"passed_time":1.301352461,"remaining_time":0.9737392538},
{"learn":[0.08740723288],"iteration":572,"passed_time":1.303587728,"remaining_time":0.9714344852},
{"learn":[0.08723341992],"iteration":573,"passed_time":1.305773445,"remaining_time":0.9690931843},
{"learn":[0.08716858898],"iteration":574,"passed_time":1.30802631,"remaining_time":0.9668020551},
{"learn":[0.0869929501],"iteration":575,"passed_time":1.31024015,"remaining_time":0.9644823325},
{"learn":[0.08686088622],"iteration":576,"passed_time":1.312494456,"remaining_time":0.962192643},
{"learn":[0.08670962896],"iteration":577,"passed_time":1.314694318,"remaining_time":0.9598633254},
{"learn":[0.08655132314],"iteration":578,"passed_time":1.31687885,"remaining_time":0.9575233089},
{"learn":[0.08645510842],"iteration":579,"passed_time":1.319206575,"remaining_time":0.95528752},
{"learn":[0.08622169329],"iteration":580,"passed_time":1.321384893,"remaining_time":0.9529436661},
{"learn":[0.08613118889],"iteration":581,"passed_time":1.323641213,"remaining_time":0.950656404},
{"learn":[0.08598681814],"iteration":582,"passed_time":1.325937737,"remaining_time":0.9483980043},
{"learn":[0.08592088515],"iteration":583,"passed_time":1.328169016,"remaining_time":0.946092998},
{"learn":[0.08576833652],"iteration":584,"passed_time":1.330362295,"remaining_time":0.9437612865},
{"learn":[0.08573657319],"iteration":585,"passed_time":1.332500952,"remaining_time":0.9413914579},
{"learn":[0.08558350713],"iteration":586,"passed_time":1.334724741,"remaining_time":0.9390823134},
{"learn":[0.08546194244],"iteration":587,"passed_time":1.3370254,"remaining_time":0.9368273213},
{"learn":[0.0854256234],"iteration":588,"passed_time":1.339191431,"remaining_time":0.9344782313},
{"learn":[0.08524764193],"iteration":589,"passed_time":1.341402876,"remaining_time":0.9321613203},
{"learn":[0.08510921238],"iteration":590,"passed_time":1.343598591,"remaining_time":0.9298338812},
{"learn":[0.08500921971],"iteration":591,"passed_time":1.345918619,"remaining_time":0.927592562},
{"learn":[0.08478189742],"iteration":592,"passed_time":1.348084321,"remaining_time":0.9252450571},
{"learn":[0.08469440258],"iteration":593,"passed_time":1.350240425,"remaining_time":0.9228916034},
{"learn":[0.08459578897],"iteration":594,"passed_time":1.352450203,"remaining_time":0.9205753483},
{"learn":[0.08456171034],"iteration":595,"passed_time":1.354636874,"remaining_time":0.9182437874},
{"learn":[0.08439233258],"iteration":596,"passed_time":1.356697619,"remaining_time":0.9158277057},
{"learn":[0.08428726227],"iteration":597,"passed_time":1.358819609,"remaining_time":0.9134539848},
{"learn":[0.08408848017],"iteration":598,"passed_time":1.361023974,"remaining_time":0.9111362497},
{"learn":[0.08401596807],"iteration":599,"passed_time":1.363260745,"remaining_time":0.9088404964},
{"learn":[0.08387572382],"iteration":600,"passed_time":1.365433985,"remaining_time":0.9065027619},
{"learn":[0.08373097128],"iteration":601,"passed_time":1.367718395,"remaining_time":0.9042390721},
{"learn":[0.08365910671],"iteration":602,"passed_time":1.369981539,"remaining_time":0.9019613117},
{"learn":[0.0834569014],"iteration":603,"passed_time":1.372219424,"remaining_time":0.8996670393},
{"learn":[0.0834087782],"iteration":604,"passed_time":1.374301472,"remaining_time":0.8972712088},
{"learn":[0.08331021783],"iteration":605,"passed_time":1.376507027,"remaining_time":0.8949567138},
{"learn":[0.08325095284],"iteration":606,"passed_time":1.378664291,"remaining_time":0.8926113118},
{"learn":[0.08321105859],"iteration":607,"passed_time":1.3845226,"remaining_time":0.8926527288},
{"learn":[0.08308755529],"iteration":608,"passed_time":1.386862251,"remaining_time":0.8904156655},
{"learn":[0.08288691465],"iteration":609,"passed_time":1.38912384,"remaining_time":0.8881283566},
{"learn":[0.0827820725],"iteration":610,"passed_time":1.391353173,"remaining_time":0.8858205961},
{"learn":[0.08268481297],"iteration":611,"passed_time":1.39355759,"remaining_time":0.8834972954},
{"learn":[0.08259634783],"iteration":612,"passed_time":1.395814812,"remaining_time":0.8812077201},
{"learn":[0.08244389385],"iteration":613,"passed_time":1.39804283,"remaining_time":0.87889989},
{"learn":[0.08224565536],"iteration":614,"passed_time":1.400179811,"remaining_time":0.876535329},
{"learn":[0.08214436219],"iteration":615,"passed_time":1.402328927,"remaining_time":0.8741790715},
{"learn":[0.08206013008],"iteration":616,"passed_time":1.404494019,"remaining_time":0.8718334025},
{"learn":[0.08184190796],"iteration":617,"passed_time":1.406686752,"remaining_time":0.8695054031},
{"learn":[0.08169121492],"iteration":618,"passed_time":1.408907214,"remaining_time":0.8671949088},
{"learn":[0.08165036159],"iteration":619,"passed_time":1.411175347,"remaining_time":0.8649139222},
{"learn":[0.08149893672],"iteration":620,"passed_time":1.413465512,"remaining_time":0.8626464235},
{"learn":[0.081384191],"iteration":621,"passed_time":1.415696069,"remaining_time":0.8603426272},
{"learn":[0.08128879009],"iteration":622,"passed_time":1.417896069,"remaining_time":0.858020575},
{"learn":[0.08128175823],"iteration":623,"passed_time":1.419178305,"remaining_time":0.8551459017},
{"learn":[0.08124542963],"iteration":624,"passed_time":1.421412804,"remaining_time":0.8528476826},
{"learn":[0.08107676262],"iteration":625,"passed_time":1.423496346,"remaining_time":0.8504594783},
{"learn":[0.08104605478],"iteration":626,"passed_time":1.425535206,"remaining_time":0.8480456648},
{"learn":[0.08096025362],"iteration":627,"passed_time":1.427677667,"remaining_time":0.8456944141},
{"learn":[0.08082798138],"iteration":628,"passed_time":1.429898445,"remaining_time":0.843390021},
{"learn":[0.08077171145],"iteration":629,"passed_time":1.432176878,"remaining_time":0.8411197537},
{"learn":[0.08072633975],"iteration":630,"passed_time":1.434336036,"remaining_time":0.8387797103},
{"learn":[0.08057274875],"iteration":631,"passed_time":1.436522464,"remaining_time":0.8364561182},
{"learn":[0.08046712473],"iteration":632,"passed_time":1.438765257,"remaining_time":0.834165639},
{"learn":[0.08043866082],"iteration":633,"passed_time":1.440943528,"remaining_time":0.831838062},
{"learn":[0.08034232097],"iteration":634,"passed_time":1.443118625,"remaining_time":0.8295091307},
{"learn":[0.08026406784],"iteration":635,"passed_time":1.445332175,"remaining_time":0.8272026911},
{"learn":[0.08022678511],"iteration":636,"passed_time":1.447486968,"remaining_time":0.8248630603},
{"learn":[0.08018356714],"iteration":637,"passed_time":1.449739179,"remaining_time":0.8225792833},
{"learn":[0.08010130575],"iteration":638,"passed_time":1.451941946,"remaining_time":0.8202676724},
{"learn":[0.07994223201],"iteration":639,"passed_time":1.454216786,"remaining_time":0.8179969424},
{"learn":[0.07984495144],"iteration":640,"passed_time":1.456518126,"remaining_time":0.8157410411},
{"learn":[0.07976434634],"iteration":641,"passed_time":1.458692179,"remaining_time":0.8134140187},
{"learn":[0.07970678995],"iteration":642,"passed_time":1.460786557,"remaining_time":0.8110432362},
{"learn":[0.07958031915],"iteration":643,"passed_time":1.462893342,"remaining_time":0.8086801705},
{"learn":[0.07949529886],"iteration":644,"passed_time":1.465034431,"remaining_time":0.8063367798},
{"learn":[0.07945265605],"iteration":645,"passed_time":1.467144941,"remaining_time":0.8039772587},
{"learn":[0.07934980393],"iteration":646,"passed_time":1.469354752,"remaining_time":0.8016726855},
{"learn":[0.07928312754],"iteration":647,"passed_time":1.471645672,"remaining_time":0.7994124636},
{"learn":[0.07921433812],"iteration":648,"passed_time":1.473892406,"remaining_time":0.7971282504},
{"learn":[0.07914448204],"iteration":649,"passed_time":1.476101651,"remaining_time":0.794823966},
{"learn":[0.07904855023],"iteration":650,"passed_time":1.478242118,"remaining_time":0.7924831016},
{"learn":[0.07888655878],"iteration":651,"passed_time":1.480483861,"remaining_time":0.7901969074},
{"learn":[0.0788000602],"iteration":652,"passed_time":1.482674073,"remaining_time":0.7878834663},
{"learn":[0.07868310714],"iteration":653,"passed_time":1.484831601,"remaining_time":0.7855531099},
{"learn":[0.0785286658],"iteration":654,"passed_time":1.486879321,"remaining_time":0.7831654436},
{"learn":[0.07837825824],"iteration":655,"passed_time":1.489105507,"remaining_time":0.7808724002},
{"learn":[0.07827420817],"iteration":656,"passed_time":1.491275753,"remaining_time":0.778550355},
{"learn":[0.07818637547],"iteration":657,"passed_time":1.493262743,"remaining_time":0.7761335228},
{"learn":[0.07808558699],"iteration":658,"passed_time":1.495577413,"remaining_time":0.7738875535},
{"learn":[0.0780633483],"iteration":659,"passed_time":1.497806592,"remaining_time":0.7715973353},
{"learn":[0.07795656079],"iteration":660,"passed_time":1.499981324,"remaining_time":0.7692793781},
{"learn":[0.07782248527],"iteration":661,"passed_time":1.502083577,"remaining_time":0.7669248473},
{"learn":[0.07766522538],"iteration":662,"passed_time":1.504382501,"remaining_time":0.7646710452},
{"learn":[0.07758076625],"iteration":663,"passed_time":1.506578258,"remaining_time":0.7623649015},
{"learn":[0.07752267518],"iteration":664,"passed_time":1.508831725,"remaining_time":0.7600881624},
{"learn":[0.0774192767],"iteration":665,"passed_time":1.51099111,"remaining_time":0.7577643103},
{"learn":[0.07726136559],"iteration":666,"passed_time":1.513228162,"remaining_time":0.7554797273},
{"learn":[0.07717612824],"iteration":667,"passed_time":1.515504659,"remaining_time":0.7532148904},
{"learn":[0.07705653777],"iteration":668,"passed_time":1.517799378,"remaining_time":0.7509590344},
{"learn":[0.07704883716],"iteration":669,"passed_time":1.519111488,"remaining_time":0.7482190909},
{"learn":[0.07699648243],"iteration":670,"passed_time":1.521203925,"remaining_time":0.7458660081},
{"learn":[0.0768404071],"iteration":671,"passed_time":1.523357858,"remaining_time":0.7435437164},
{"learn":[0.07672476984],"iteration":672,"passed_time":1.525579859,"remaining_time":0.7412549983},
{"learn":[0.07666636949],"iteration":673,"passed_time":1.527823114,"remaining_time":0.7389767585},
{"learn":[0.07662541943],"iteration":674,"passed_time":1.529953515,"remaining_time":0.736644285},
{"learn":[0.07652057998],"iteration":675,"passed_time":1.532188366,"remaining_time":0.7343624714},
{"learn":[0.07632976074],"iteration":676,"passed_time":1.534374052,"remaining_time":0.7320573394},
{"learn":[0.07629688815],"iteration":677,"passed_time":1.536512752,"remaining_time":0.7297302453},
{"learn":[0.07617067979],"iteration":678,"passed_time":1.538724513,"remaining_time":0.7274382454},
{"learn":[0.07605249636],"iteration":679,"passed_time":1.540911453,"remaining_time":0.7251348014},
{"learn":[0.07583814426],"iteration":680,"passed_time":1.543087825,"remaining_time":0.7228267492},
{"learn":[0.0757473549],"iteration":681,"passed_time":1.545359209,"remaining_time":0.7205633847},
{"learn":[0.07564135922],"iteration":682,"passed_time":1.547496378,"remaining_time":0.7182377041},
{"learn":[0.07563724799],"iteration":683,"passed_time":1.548107332,"remaining_time":0.7152074808},
{"learn":[0.07560112239],"iteration":684,"passed_time":1.550375368,"remaining_time":0.7129463372},
{"learn":[0.07556670736],"iteration":685,"passed_time":1.552602852,"remaining_time":0.7106666116},
{"learn":[0.07543715839],"iteration":686,"passed_time":1.554842835,"remaining_time":0.7083927327},
{"learn":[0.07530650211],"iteration":687,"passed_time":1.556995468,"remaining_time":0.7060793402},
{"learn":[0.07524603818],"iteration":688,"passed_time":1.559117625,"remaining_time":0.7037526581},
{"learn":[0.07514073492],"iteration":689,"passed_time":1.561279549,"remaining_time":0.701444435},
{"learn":[0.07498745317],"iteration":690,"passed_time":1.563404205,"remaining_time":0.6991199702},
{"learn":[0.07489168351],"iteration":691,"passed_time":1.565607026,"remaining_time":0.696830873},
{"learn":[0.07484586837],"iteration":692,"passed_time":1.567832575,"remaining_time":0.6945520931},
{"learn":[0.07470182905],"iteration":693,"passed_time":1.570068644,"remaining_time":0.6922781053},
{"learn":[0.07460194964],"iteration":694,"passed_time":1.572179449,"remaining_time":0.6899492547},
{"learn":[0.07448976184],"iteration":695,"passed_time":1.574403217,"remaining_time":0.6876703706},
{"learn":[0.07445324768],"iteration":696,"passed_time":1.576690064,"remaining_time":0.6854190667},
{"learn":[0.07436758387],"iteration":697,"passed_time":1.578968595,"remaining_time":0.6831640626},
{"learn":[0.07419598618],"iteration":698,"passed_time":1.581181314,"remaining_time":0.6808806518},
{"learn":[0.07416634451],"iteration":699,"passed_time":1.583416789,"remaining_time":0.6786071954},
{"learn":[0.07414549628],"iteration":700,"passed_time":1.585587573,"remaining_time":0.6763062543},
{"learn":[0.07404460828],"iteration":701,"passed_time":1.587719444,"remaining_time":0.6739891655},
{"learn":[0.07393907446],"iteration":702,"passed_time":1.589930711,"remaining_time":0.6717061467},
{"learn":[0.07391838347],"iteration":703,"passed_time":1.592151621,"remaining_time":0.6694273862},
{"learn":[0.07382752006],"iteration":704,"passed_time":1.594329841,"remaining_time":0.6671309264},
{"learn":[0.07370970368],"iteration":705,"passed_time":1.596484995,"remaining_time":0.6648251963},
{"learn":[0.07365669188],"iteration":706,"passed_time":1.598696809,"remaining_time":0.6625433733},
{"learn":[0.07362808965],"iteration":707,"passed_time":1.60098256,"remaining_time":0.6602922422},
{"learn":[0.07350577508],"iteration":708,"passed_time":1.603238681,"remaining_time":0.658028852},
{"learn":[0.07339215466],"iteration":709,"passed_time":1.605488172,"remaining_time":0.6557627743},
{"learn":[0.07333570866],"iteration":710,"passed_time":1.607645243,"remaining_time":0.6534591775},
{"learn":[0.07320221829],"iteration":711,"passed_time":1.609858543,"remaining_time":0.6511787365},
{"learn":[0.0730843805],"iteration":712,"passed_time":1.611997055,"remaining_time":0.6488683798},
{"learn":[0.07295805326],"iteration":713,"passed_time":1.614185413,"remaining_time":0.6465784708},
{"learn":[0.07293512439],"iteration":714,"passed_time":1.61634946,"remaining_time":0.6442791554},
{"learn":[0.07288561733],"iteration":715,"passed_time":1.618484754,"remaining_time":0.6419688129},
{"learn":[0.07285655172],"iteration":716,"passed_time":1.620675881,"remaining_time":0.6396809962},
{"learn":[0.07281967431],"iteration":717,"passed_time":1.62287186,"remaining_time":0.6373953544},
{"learn":[0.0726665918],"iteration":718,"passed_time":1.625001565,"remaining_time":0.6350840608},
{"learn":[0.0725140103],"iteration":719,"passed_time":1.627180057,"remaining_time":0.6327922445},
{"learn":[0.0724937559],"iteration":720,"passed_time":1.629353837,"remaining_time":0.630498919},
{"learn":[0.07240501837],"iteration":721,"passed_time":1.631502379,"remaining_time":0.6281962069},
{"learn":[0.0723548345],"iteration":722,"passed_time":1.633563158,"remaining_time":0.6258602971},
{"learn":[0.07215222708],"iteration":723,"passed_time":1.635928592,"remaining_time":0.6236412866},
{"learn":[0.07210377652],"iteration":724,"passed_time":1.63811504,"remaining_time":0.6213539807},
{"learn":[0.07206118162],"iteration":725,"passed_time":1.640283998,"remaining_time":0.6190603518},
{"learn":[0.07194788919],"iteration":726,"passed_time":1.642471588,"remaining_time":0.6167740626},
{"learn":[0.07183754675],"iteration":727,"passed_time":1.644672202,"remaining_time":0.6144929106},
{"learn":[0.07168622855],"iteration":728,"passed_time":1.646820986,"remaining_time":0.6121927121},
{"learn":[0.07160810098],"iteration":729,"passed_time":1.649035561,"remaining_time":0.6099172625},
{"learn":[0.07143464166],"iteration":730,"passed_time":1.651125752,"remaining_time":0.6075962071},
{"learn":[0.07133469626],"iteration":731,"passed_time":1.653426555,"remaining_time":0.6053528917},
{"learn":[0.07131253338],"iteration":732,"passed_time":1.655580904,"remaining_time":0.6030560728},
{"learn":[0.07123138031],"iteration":733,"passed_time":1.657812892,"remaining_time":0.6007877782},
{"learn":[0.07112314043],"iteration":734,"passed_time":1.659919722,"remaining_time":0.5984744577},
{"learn":[0.07109274103],"iteration":735,"passed_time":1.66208413,"remaining_time":0.596182351},
{"learn":[0.07097126729],"iteration":736,"passed_time":1.664293206,"remaining_time":0.5939065308},
{"learn":[0.07089541674],"iteration":737,"passed_time":1.666413683,"remaining_time":0.5915994376},
{"learn":[0.07080638465],"iteration":738,"passed_time":1.668680179,"remaining_time":0.5893444205},
{"learn":[0.07073068223],"iteration":739,"passed_time":1.670892403,"remaining_time":0.5870703039},
{"learn":[0.07065318922],"iteration":740,"passed_time":1.673107542,"remaining_time":0.5847973729},
{"learn":[0.07055826118],"iteration":741,"passed_time":1.675317162,"remaining_time":0.5825226789},
{"learn":[0.07046986235],"iteration":742,"passed_time":1.677526349,"remaining_time":0.5802480103},
{"learn":[0.07035005285],"iteration":743,"passed_time":1.67978551,"remaining_time":0.5779907132},
{"learn":[0.0703032009],"iteration":744,"passed_time":1.68204033,"remaining_time":0.5757319252},
{"learn":[0.07026586317],"iteration":745,"passed_time":1.684253655,"remaining_time":0.5734590191},
{"learn":[0.0701199539],"iteration":746,"passed_time":1.68644853,"remaining_time":0.5711800241},
{"learn":[0.0700789389],"iteration":747,"passed_time":1.68851258,"remaining_time":0.5688571794},
{"learn":[0.06999843906],"iteration":748,"passed_time":1.69071224,"remaining_time":0.5665804704},
{"learn":[0.06997551065],"iteration":749,"passed_time":1.692961408,"remaining_time":0.5643204693},
{"learn":[0.06996427312],"iteration":750,"passed_time":1.694273933,"remaining_time":0.5617499458},
{"learn":[0.0698597104],"iteration":751,"passed_time":1.696468732,"remaining_time":0.5594737307},
{"learn":[0.06974284089],"iteration":752,"passed_time":1.698714764,"remaining_time":0.5572145374},
{"learn":[0.06957783939],"iteration":753,"passed_time":1.700907725,"remaining_time":0.554938064},
{"learn":[0.06954397699],"iteration":754,"passed_time":1.703132912,"remaining_time":0.5526722694},
{"learn":[0.0694288341],"iteration":755,"passed_time":1.705250895,"remaining_time":0.550371982},
{"learn":[0.06941482503],"iteration":756,"passed_time":1.707222904,"remaining_time":0.5480253178},
{"learn":[0.06927600636],"iteration":757,"passed_time":1.709411053,"remaining_time":0.5457486474},
{"learn":[0.06920949597],"iteration":758,"passed_time":1.711719026,"remaining_time":0.5435102573},
{"learn":[0.06917044715],"iteration":759,"passed_time":1.713967391,"remaining_time":0.5412528603},
{"learn":[0.06904464886],"iteration":760,"passed_time":1.716164744,"remaining_time":0.5389794662},
{"learn":[0.06900031024],"iteration":761,"passed_time":1.718243802,"remaining_time":0.5366693239},
{"learn":[0.06889064785],"iteration":762,"passed_time":1.72032603,"remaining_time":0.534360772},
{"learn":[0.06877226496],"iteration":763,"passed_time":1.722518093,"remaining_time":0.5320867408},
{"learn":[0.06870831473],"iteration":764,"passed_time":1.72473647,"remaining_time":0.5298210071},
{"learn":[0.06853917791],"iteration":765,"passed_time":1.726924423,"remaining_time":0.5275461031},
{"learn":[0.06853478544],"iteration":766,"passed_time":1.729083777,"remaining_time":0.5252627379},
{"learn":[0.06848900464],"iteration":767,"passed_time":1.731230608,"remaining_time":0.5229759128},
{"learn":[0.06840218043],"iteration":768,"passed_time":1.733405115,"remaining_time":0.5206977653},
{"learn":[0.06829354935],"iteration":769,"passed_time":1.735571212,"remaining_time":0.518417375},
{"learn":[0.06820626987],"iteration":770,"passed_time":1.73771835,"remaining_time":0.5161316499},
{"learn":[0.06812238066],"iteration":771,"passed_time":1.739884509,"remaining_time":0.5138519016},
{"learn":[0.06803499739],"iteration":772,"passed_time":1.741961203,"remaining_time":0.5115461747},
{"learn":[0.06793932106],"iteration":773,"passed_time":1.744164569,"remaining_time":0.5092780267},
{"learn":[0.06789609227],"iteration":774,"passed_time":1.746273996,"remaining_time":0.5069827731},
{"learn":[0.06780982484],"iteration":775,"passed_time":1.748465612,"remaining_time":0.504711723},
{"learn":[0.06770540036],"iteration":776,"passed_time":1.750658284,"remaining_time":0.5024411805},
{"learn":[0.06768899132],"iteration":777,"passed_time":1.752788047,"remaining_time":0.5001528876},
{"learn":[0.06762314065],"iteration":778,"passed_time":1.754991527,"remaining_time":0.4978859147},
{"learn":[0.06756301918],"iteration":779,"passed_time":1.757161079,"remaining_time":0.495609535},
{"learn":[0.06747495429],"iteration":780,"passed_time":1.759279328,"remaining_time":0.4933190433},
{"learn":[0.06744416],"iteration":781,"passed_time":1.761346795,"remaining_time":0.4910148355},
{"learn":[0.06734529933],"iteration":782,"passed_time":1.763528101,"remaining_time":0.4887427814},
{"learn":[0.06728186999],"iteration":783,"passed_time":1.765570159,"remaining_time":0.4864325948},
{"learn":[0.06717226214],"iteration":784,"passed_time":1.767790518,"remaining_time":0.4841719254},
{"learn":[0.06707003587],"iteration":785,"passed_time":1.770106553,"remaining_time":0.4819374076},
{"learn":[0.067068393],"iteration":786,"passed_time":1.772239789,"remaining_time":0.4796532085},
{"learn":[0.06697680855],"iteration":787,"passed_time":1.77432164,"remaining_time":0.4773555682},
{"learn":[0.06688388714],"iteration":788,"passed_time":1.77643912,"remaining_time":0.4750680028},
{"learn":[0.06675745633],"iteration":789,"passed_time":1.778610205,"remaining_time":0.4727951178},
{"learn":[0.06675420669],"iteration":790,"passed_time":1.779225508,"remaining_time":0.4701114175},
{"learn":[0.06666486999],"iteration":791,"passed_time":1.781320959,"remaining_time":0.4678216659},
{"learn":[0.0665679987],"iteration":792,"passed_time":1.783484259,"remaining_time":0.4655501155},
{"learn":[0.06651642136],"iteration":793,"passed_time":1.785709751,"remaining_time":0.4632949733},
{"learn":[0.06650955151],"iteration":794,"passed_time":1.787030996,"remaining_time":0.4608067348},
{"learn":[0.06649008917],"iteration":795,"passed_time":1.789272156,"remaining_time":0.4585571858},
{"learn":[0.06644958875],"iteration":796,"passed_time":1.79152686,"remaining_time":0.4563111074},
{"learn":[0.06641043392],"iteration":797,"passed_time":1.793721059,"remaining_time":0.4540496918},
{"learn":[0.0662741588],"iteration":798,"passed_time":1.795909264,"remaining_time":0.4517869362},
{"learn":[0.06627020609],"iteration":799,"passed_time":1.797944244,"remaining_time":0.449486061},
{"learn":[0.06620981939],"iteration":800,"passed_time":1.799999758,"remaining_time":0.4471909512},
{"learn":[0.06613882418],"iteration":801,"passed_time":1.80219977,"remaining_time":0.4449321128},
{"learn":[0.06601230093],"iteration":802,"passed_time":1.804357592,"remaining_time":0.4426630705},
{"learn":[0.06589599538],"iteration":803,"passed_time":1.806558389,"remaining_time":0.4404047814},
{"learn":[0.06582047852],"iteration":804,"passed_time":1.808702131,"remaining_time":0.4381328143},
{"learn":[0.0658144556],"iteration":805,"passed_time":1.810885131,"remaining_time":0.4358706146},
{"learn":[0.06565481529],"iteration":806,"passed_time":1.813146854,"remaining_time":0.4336274385},
{"learn":[0.06555985267],"iteration":807,"passed_time":1.815348531,"remaining_time":0.431369948},
{"learn":[0.0654497169],"iteration":808,"passed_time":1.817561014,"remaining_time":0.4291151467},
{"learn":[0.06541633901],"iteration":809,"passed_time":1.819707049,"remaining_time":0.4268448634},
{"learn":[0.06539498714],"iteration":810,"passed_time":1.821907273,"remaining_time":0.4245875149},
{"learn":[0.06528020569],"iteration":811,"passed_time":1.824020437,"remaining_time":0.4223101505},
{"learn":[0.0651617233],"iteration":812,"passed_time":1.826288337,"remaining_time":0.4200687812},
{"learn":[0.06512536538],"iteration":813,"passed_time":1.82847602,"remaining_time":0.4178090168},
{"learn":[0.0649847787],"iteration":814,"passed_time":1.830648153,"remaining_time":0.4155458996},
{"learn":[0.06498217975],"iteration":815,"passed_time":1.832768867,"remaining_time":0.4132714113},
{"learn":[0.06488746879],"iteration":816,"passed_time":1.834952167,"remaining_time":0.4110113176},
{"learn":[0.06479117797],"iteration":817,"passed_time":1.837201232,"remaining_time":0.4087660443},
{"learn":[0.06478185036],"iteration":818,"passed_time":1.839427474,"remaining_time":0.4065157178},
{"learn":[0.0646808073],"iteration":819,"passed_time":1.841641482,"remaining_time":0.4042627644},
{"learn":[0.06462026225],"iteration":820,"passed_time":1.843824537,"remaining_time":0.4020031574},
{"learn":[0.06455089822],"iteration":821,"passed_time":1.84602013,"remaining_time":0.3997464515},
{"learn":[0.06449451515],"iteration":822,"passed_time":1.848329281,"remaining_time":0.3975143168},
{"learn":[0.06433894823],"iteration":823,"passed_time":1.850524663,"remaining_time":0.395257695},
{"learn":[0.06424612069],"iteration":824,"passed_time":1.852717161,"remaining_time":0.3930006099},
{"learn":[0.06411570098],"iteration":825,"passed_time":1.854988191,"remaining_time":0.3907602242},
{"learn":[0.06408506215],"iteration":826,"passed_time":1.857224373,"remaining_time":0.3885124747},
{"learn":[0.06402090007],"iteration":827,"passed_time":1.85942384,"remaining_time":0.3862571261},
{"learn":[0.06392343207],"iteration":828,"passed_time":1.861557705,"remaining_time":0.3839883807},
{"learn":[0.06381527981],"iteration":829,"passed_time":1.86373326,"remaining_time":0.3817284989},
{"learn":[0.06376661125],"iteration":830,"passed_time":1.865852914,"remaining_time":0.3794574518},
{"learn":[0.06364560744],"iteration":831,"passed_time":1.868087211,"remaining_time":0.3772099177},
{"learn":[0.06352242894],"iteration":832,"passed_time":1.870341643,"remaining_time":0.3749664519},
{"learn":[0.06341818952],"iteration":833,"passed_time":1.87256704,"remaining_time":0.3727171807},
{"learn":[0.06341501284],"iteration":834,"passed_time":1.87389728,"remaining_time":0.3702910793},
{"learn":[0.06338877814],"iteration":835,"passed_time":1.876105377,"remaining_time":0.3680398107},
{"learn":[0.06326662393],"iteration":836,"passed_time":1.878200906,"remaining_time":0.3657667237},
{"learn":[0.06319580204],"iteration":837,"passed_time":1.880315972,"remaining_time":0.363497837},
{"learn":[0.06319346516],"iteration":838,"passed_time":1.882347272,"remaining_time":0.361213243},
{"learn":[0.06316824437],"iteration":839,"passed_time":1.884522191,"remaining_time":0.3589566078},
{"learn":[0.06308378713],"iteration":840,"passed_time":1.886665452,"remaining_time":0.3566941817},
{"learn":[0.0630544113],"iteration":841,"passed_time":1.888927792,"remaining_time":0.3544543838},
{"learn":[0.06295663201],"iteration":842,"passed_time":1.891108234,"remaining_time":0.3521992797},
{"learn":[0.06282661766],"iteration":843,"passed_time":1.893184027,"remaining_time":0.3499250097},
{"learn":[0.06271271819],"iteration":844,"passed_time":1.895278127,"remaining_time":0.3476545676},
{"learn":[0.06262706884],"iteration":845,"passed_time":1.897512932,"remaining_time":0.3454101555},
{"learn":[0.06260459966],"iteration":846,"passed_time":1.899608734,"remaining_time":0.3431406567},
{"learn":[0.06252778929],"iteration":847,"passed_time":1.901710606,"remaining_time":0.3408726557},
{"learn":[0.06252168624],"iteration":848,"passed_time":1.903715632,"remaining_time":0.3385878214},
{"learn":[0.06238686437],"iteration":849,"passed_time":1.905823932,"remaining_time":0.3363218703},
{"learn":[0.06232959852],"iteration":850,"passed_time":1.908016899,"remaining_time":0.3340711139},
{"learn":[0.06226074144],"iteration":851,"passed_time":1.910180048,"remaining_time":0.3318153135},
{"learn":[0.06220413079],"iteration":852,"passed_time":1.912428777,"remaining_time":0.3295744786},
{"learn":[0.06220101483],"iteration":853,"passed_time":1.913278961,"remaining_time":0.3270945297},
{"learn":[0.06208450884],"iteration":854,"passed_time":1.91559559,"remaining_time":0.3248670884},
{"learn":[0.06199988487],"iteration":855,"passed_time":1.917819276,"remaining_time":0.3226238034},
{"learn":[0.06194244754],"iteration":856,"passed_time":1.920011082,"remaining_time":0.3203752447},
{"learn":[0.06187553733],"iteration":857,"passed_time":1.922230347,"remaining_time":0.3181313629},
{"learn":[0.06178067426],"iteration":858,"passed_time":1.924304417,"remaining_time":0.3158637052},
{"learn":[0.06171933159],"iteration":859,"passed_time":1.926410886,"remaining_time":0.3136017721},
{"learn":[0.06161626753],"iteration":860,"passed_time":1.928632614,"remaining_time":0.3113588076},
{"learn":[0.06153568377],"iteration":861,"passed_time":1.930697908,"remaining_time":0.3090908484},
{"learn":[0.06150835496],"iteration":862,"passed_time":1.93279341,"remaining_time":0.3068281544},
{"learn":[0.0614356455],"iteration":863,"passed_time":1.935018583,"remaining_time":0.3045862584},
{"learn":[0.06134414678],"iteration":864,"passed_time":1.937143102,"remaining_time":0.3023286922},
{"learn":[0.0612309574],"iteration":865,"passed_time":1.939289586,"remaining_time":0.300074832},
{"learn":[0.06120361996],"iteration":866,"passed_time":1.941412711,"remaining_time":0.2978176362},
{"learn":[0.06119390334],"iteration":867,"passed_time":1.943521103,"remaining_time":0.2955585087},
{"learn":[0.06113716554],"iteration":868,"passed_time":1.945675249,"remaining_time":0.2933066256},
{"learn":[0.06107534206],"iteration":869,"passed_time":1.947902322,"remaining_time":0.2910658642},
{"learn":[0.06096331839],"iteration":870,"passed_time":1.95017224,"remaining_time":0.2888314799},
{"learn":[0.0609588752],"iteration":871,"passed_time":1.952424579,"remaining_time":0.2865944337},
{"learn":[0.06093283026],"iteration":872,"passed_time":1.954642026,"remaining_time":0.2843522764},
{"learn":[0.06090172652],"iteration":873,"passed_time":1.956805516,"remaining_time":0.2821023971},
{"learn":[0.06078487198],"iteration":874,"passed_time":1.95899041,"remaining_time":0.2798557729},
{"learn":[0.0607334729],"iteration":875,"passed_time":1.961314473,"remaining_time":0.2776289893},
{"learn":[0.06066695984],"iteration":876,"passed_time":1.963536579,"remaining_time":0.2753876844},
{"learn":[0.06058932851],"iteration":877,"passed_time":1.965815555,"remaining_time":0.2731543255},
{"learn":[0.06048500084],"iteration":878,"passed_time":1.968006913,"remaining_time":0.2709088014},
{"learn":[0.06047811383],"iteration":879,"passed_time":1.970066752,"remaining_time":0.2686454662},
{"learn":[0.06044913812],"iteration":880,"passed_time":1.972219357,"remaining_time":0.2663951231},
{"learn":[0.06035264154],"iteration":881,"passed_time":1.974480689,"remaining_time":0.2641595479},
{"learn":[0.06030373642],"iteration":882,"passed_time":1.976642977,"remaining_time":0.2619107909},
{"learn":[0.06027273804],"iteration":883,"passed_time":1.978833129,"remaining_time":0.2596658857},
{"learn":[0.06016067475],"iteration":884,"passed_time":1.980948952,"remaining_time":0.2574114457},
{"learn":[0.06009192108],"iteration":885,"passed_time":1.983054196,"remaining_time":0.2551559574},
{"learn":[0.06007209444],"iteration":886,"passed_time":1.985321258,"remaining_time":0.2529214229},
{"learn":[0.06000832058],"iteration":887,"passed_time":1.987472243,"remaining_time":0.2506721748},
{"learn":[0.05994775433],"iteration":888,"passed_time":1.989619049,"remaining_time":0.2484226259},
{"learn":[0.05987960842],"iteration":889,"passed_time":1.991821479,"remaining_time":0.2461801828},
{"learn":[0.0598569841],"iteration":890,"passed_time":1.994057178,"remaining_time":0.2439418995},
{"learn":[0.05979843479],"iteration":891,"passed_time":1.996281712,"remaining_time":0.2417022701},
{"learn":[0.05976850627],"iteration":892,"passed_time":1.998559336,"remaining_time":0.2394690358},
{"learn":[0.05970968957],"iteration":893,"passed_time":2.000598792,"remaining_time":0.2372074631},
{"learn":[0.05964514831],"iteration":894,"passed_time":2.002782646,"remaining_time":0.2349633271},
{"learn":[0.05955466818],"iteration":895,"passed_time":2.004977224,"remaining_time":0.2327205706},
{"learn":[0.05955236063],"iteration":896,"passed_time":2.005435148,"remaining_time":0.2302785064},
{"learn":[0.05943398909],"iteration":897,"passed_time":2.007668243,"remaining_time":0.2280424953},
{"learn":[0.05935865043],"iteration":898,"passed_time":2.009804985,"remaining_time":0.2257956657},
{"learn":[0.05925268968],"iteration":899,"passed_time":2.011971671,"remaining_time":0.2235524079},
{"learn":[0.05920033718],"iteration":900,"passed_time":2.014285443,"remaining_time":0.2213254815},
{"learn":[0.059134442],"iteration":901,"passed_time":2.01657455,"remaining_time":0.2190956829},
{"learn":[0.05904166732],"iteration":902,"passed_time":2.018731767,"remaining_time":0.2168515852},
{"learn":[0.05895455879],"iteration":903,"passed_time":2.020993718,"remaining_time":0.2146188019},
{"learn":[0.05886064979],"iteration":904,"passed_time":2.023227755,"remaining_time":0.212383024},
{"learn":[0.05883706712],"iteration":905,"passed_time":2.02541125,"remaining_time":0.2101420061},
{"learn":[0.0588322009],"iteration":906,"passed_time":2.027542618,"remaining_time":0.2078957701},
{"learn":[0.05878194185],"iteration":907,"passed_time":2.029756499,"remaining_time":0.2056581474},
{"learn":[0.05874550405],"iteration":908,"passed_time":2.031944744,"remaining_time":0.2034180107},
{"learn":[0.05869948623],"iteration":909,"passed_time":2.034174473,"remaining_time":0.2011820907},
{"learn":[0.05863262125],"iteration":910,"passed_time":2.036357216,"remaining_time":0.1989415941},
{"learn":[0.05855301885],"iteration":911,"passed_time":2.0384683,"remaining_time":0.1966943097},
{"learn":[0.05854309565],"iteration":912,"passed_time":2.040669576,"remaining_time":0.194455918},
{"learn":[0.05853628788],"iteration":913,"passed_time":2.04288036,"remaining_time":0.1922185021},
{"learn":[0.05842403166],"iteration":914,"passed_time":2.045114507,"remaining_time":0.1899833149},
{"learn":[0.05836450359],"iteration":915,"passed_time":2.047377963,"remaining_time":0.1877508176},
{"learn":[0.05830314855],"iteration":916,"passed_time":2.049569559,"remaining_time":0.1855117485},
{"learn":[0.05828463053],"iteration":917,"passed_time":2.051686633,"remaining_time":0.1832661262},
{"learn":[0.05824828154],"iteration":918,"passed_time":2.053947638,"remaining_time":0.1810334697},
{"learn":[0.05816886273],"iteration":919,"passed_time":2.056035648,"remaining_time":0.1787857085},
{"learn":[0.058084345],"iteration":920,"passed_time":2.058267318,"remaining_time":0.1765506168},
{"learn":[0.05804088985],"iteration":921,"passed_time":2.060481737,"remaining_time":0.1743140732},
{"learn":[0.05797708325],"iteration":922,"passed_time":2.062617326,"remaining_time":0.1720710012},
{"learn":[0.05789055],"iteration":923,"passed_time":2.064790062,"remaining_time":0.1698312173},
{"learn":[0.05786931152],"iteration":924,"passed_time":2.06694573,"remaining_time":0.1675901943},
{"learn":[0.05780047174],"iteration":925,"passed_time":2.069173634,"remaining_time":0.1653551284},
{"learn":[0.05775273019],"iteration":926,"passed_time":2.071475321,"remaining_time":0.1631258883},
{"learn":[0.05774884571],"iteration":927,"passed_time":2.073562279,"remaining_time":0.160879832},
{"learn":[0.05773419258],"iteration":928,"passed_time":2.075760792,"remaining_time":0.1586426439},
{"learn":[0.0576622958],"iteration":929,"passed_time":2.077879923,"remaining_time":0.1563995641},
{"learn":[0.05761035482],"iteration":930,"passed_time":2.080058931,"remaining_time":0.1541611882},
{"learn":[0.05756298973],"iteration":931,"passed_time":2.082280417,"remaining_time":0.151926039},
{"learn":[0.0574997248],"iteration":932,"passed_time":2.08462261,"remaining_time":0.1496995872},
{"learn":[0.05741912108],"iteration":933,"passed_time":2.086853549,"remaining_time":0.1474650259},
{"learn":[0.05732009205],"iteration":934,"passed_time":2.08910143,"remaining_time":0.1452316502},
{"learn":[0.0572714504],"iteration":935,"passed_time":2.091239557,"remaining_time":0.142990739},
{"learn":[0.0572183686],"iteration":936,"passed_time":2.093432239,"remaining_time":0.1407537151},
{"learn":[0.05717422811],"iteration":937,"passed_time":2.095685385,"remaining_time":0.1385207824},
{"learn":[0.0571600692],"iteration":938,"passed_time":2.097948614,"remaining_time":0.1362884616},
{"learn":[0.057140501],"iteration":939,"passed_time":2.100169546,"remaining_time":0.1340533753},
{"learn":[0.05701901568],"iteration":940,"passed_time":2.102366646,"remaining_time":0.1318168248},
{"learn":[0.05694649911],"iteration":941,"passed_time":2.10458169,"remaining_time":0.1295814629},
{"learn":[0.05691727724],"iteration":942,"passed_time":2.106846695,"remaining_time":0.127349164},
{"learn":[0.05685030936],"iteration":943,"passed_time":2.109117161,"remaining_time":0.1251171197},
{"learn":[0.05674929349],"iteration":944,"passed_time":2.111322994,"remaining_time":0.1228812324},
{"learn":[0.05668931018],"iteration":945,"passed_time":2.113562175,"remaining_time":0.1206473123},
{"learn":[0.05666002802],"iteration":946,"passed_time":2.11575627,"remaining_time":0.1184108578},
{"learn":[0.05657761032],"iteration":947,"passed_time":2.117806525,"remaining_time":0.1161666026},
{"learn":[0.05655051453],"iteration":948,"passed_time":2.119867975,"remaining_time":0.113923358},
{"learn":[0.05648600876],"iteration":949,"passed_time":2.122000979,"remaining_time":0.1116842621},
{"learn":[0.05641559692],"iteration":950,"passed_time":2.124188236,"remaining_time":0.1094481846},
{"learn":[0.05636424804],"iteration":951,"passed_time":2.126429614,"remaining_time":0.1072149385},
{"learn":[0.05631402976],"iteration":952,"passed_time":2.128619304,"remaining_time":0.1049791262},
{"learn":[0.05627347202],"iteration":953,"passed_time":2.13088833,"remaining_time":0.1027472361},
{"learn":[0.05615404812],"iteration":954,"passed_time":2.133180547,"remaining_time":0.1005163609},
{"learn":[0.05611886533],"iteration":955,"passed_time":2.135310151,"remaining_time":0.09827787307},
{"learn":[0.05606453864],"iteration":956,"passed_time":2.137407804,"remaining_time":0.09603817719},
{"learn":[0.05598397125],"iteration":957,"passed_time":2.139686004,"remaining_time":0.09380669329},
{"learn":[0.0559020236],"iteration":958,"passed_time":2.14174343,"remaining_time":0.09156567324},
{"learn":[0.05583076308],"iteration":959,"passed_time":2.143959503,"remaining_time":0.08933164595},
{"learn":[0.05582561454],"iteration":960,"passed_time":2.146148751,"remaining_time":0.08709656742},
{"learn":[0.05577164499],"iteration":961,"passed_time":2.148381048,"remaining_time":0.08486328463},
{"learn":[0.05574530002],"iteration":962,"passed_time":2.150490168,"remaining_time":0.08262527124},
{"learn":[0.05572110773],"iteration":963,"passed_time":2.152621485,"remaining_time":0.0803883542},
{"learn":[0.05566529637],"iteration":964,"passed_time":2.154716463,"remaining_time":0.07815033803},
{"learn":[0.05562104661],"iteration":965,"passed_time":2.156897668,"remaining_time":0.07591565291},
{"learn":[0.05555696528],"iteration":966,"passed_time":2.158990043,"remaining_time":0.07367804696},
{"learn":[0.05550641367],"iteration":967,"passed_time":2.161032273,"remaining_time":0.0714390834},
{"learn":[0.0554025641],"iteration":968,"passed_time":2.163310449,"remaining_time":0.06920807423},
{"learn":[0.05531425901],"iteration":969,"passed_time":2.165562226,"remaining_time":0.06697615131},
{"learn":[0.05524417751],"iteration":970,"passed_time":2.167864037,"remaining_time":0.06474568185},
{"learn":[0.05515952927],"iteration":971,"passed_time":2.170075685,"remaining_time":0.0625124683},
{"learn":[0.05510915321],"iteration":972,"passed_time":2.172395404,"remaining_time":0.06028229796},
{"learn":[0.05502503096],"iteration":973,"passed_time":2.174694549,"remaining_time":0.05805139453},
{"learn":[0.05495385305],"iteration":974,"passed_time":2.176880295,"remaining_time":0.05581744345},
{"learn":[0.05491616329],"iteration":975,"passed_time":2.179136549,"remaining_time":0.05358532498},
{"learn":[0.05483517957],"iteration":976,"passed_time":2.181305129,"remaining_time":0.05135109312},
{"learn":[0.05478910458],"iteration":977,"passed_time":2.183490627,"remaining_time":0.04911737607},
{"learn":[0.05474815207],"iteration":978,"passed_time":2.185746639,"remaining_time":0.04688527009},
{"learn":[0.05471948999],"iteration":979,"passed_time":2.187951127,"remaining_time":0.04465206383},
{"learn":[0.05462455189],"iteration":980,"passed_time":2.190112448,"remaining_time":0.04241808003},
{"learn":[0.05455591471],"iteration":981,"passed_time":2.192196913,"remaining_time":0.04018283547},
{"learn":[0.05451200822],"iteration":982,"passed_time":2.194416519,"remaining_time":0.03795023482},
{"learn":[0.05446401337],"iteration":983,"passed_time":2.196671393,"remaining_time":0.03571823403},
{"learn":[0.05444749281],"iteration":984,"passed_time":2.198880622,"remaining_time":0.0334854917},
{"learn":[0.05440535616],"iteration":985,"passed_time":2.201069651,"remaining_time":0.03125251025},
{"learn":[0.05431867402],"iteration":986,"passed_time":2.203251911,"remaining_time":0.02901952872},
{"learn":[0.05423178386],"iteration":987,"passed_time":2.205320933,"remaining_time":0.02678527449},
{"learn":[0.05413873657],"iteration":988,"passed_time":2.207420158,"remaining_time":0.02455169033},
{"learn":[0.05410776287],"iteration":989,"passed_time":2.209410169,"remaining_time":0.02231727443},
{"learn":[0.05402874149],"iteration":990,"passed_time":2.211532085,"remaining_time":0.02008454971},
{"learn":[0.05397182169],"iteration":991,"passed_time":2.213747429,"remaining_time":0.01785280185},
{"learn":[0.05388199331],"iteration":992,"passed_time":2.215897093,"remaining_time":0.01562062402},
{"learn":[0.05380863057],"iteration":993,"passed_time":2.218100602,"remaining_time":0.01338893723},
{"learn":[0.05378481746],"iteration":994,"passed_time":2.220327444,"remaining_time":0.01115742434},
{"learn":[0.05368681992],"iteration":995,"passed_time":2.222673001,"remaining_time":0.008926397594},
{"learn":[0.05367702569],"iteration":996,"passed_time":2.224979912,"remaining_time":0.00669502481},
{"learn":[0.05361359143],"iteration":997,"passed_time":2.227182003,"remaining_time":0.004463290587},
{"learn":[0.05356261861],"iteration":998,"passed_time":2.229297287,"remaining_time":0.002231528816},
{"learn":[0.05350304032],"iteration":999,"passed_time":2.231448216,"remaining_time":0}
]}